ultrasound/verilog/logc/fifo.v
module fifo #(
    parameter DATA_WIDTH = 16,
    parameter ADDR_WIDTH = 3
) (
    input  wire                  clk,
    input  wire                  reset,
    input  wire [DATA_WIDTH-1:0] data_in,
    output wire [DATA_WIDTH-1:0] data_out,
    output reg  [ADDR_WIDTH:0]   fifo_count,
    output reg  [ADDR_WIDTH-1:0] rd_ptr,
    output reg  [ADDR_WIDTH-1:0] wr_ptr
);

    localparam DEPTH = 1 << ADDR_WIDTH;

    reg [DATA_WIDTH-1:0] fifo_mem [0:DEPTH-1];

    // Combinational read — instant update when rd_ptr changes
    assign data_out = fifo_mem[rd_ptr];

    always @(posedge clk or posedge reset) begin
        if (reset) begin
            rd_ptr     <= 0;
            wr_ptr     <= 0;
            fifo_count <= 0;
        end else begin
            // Example: write when FIFO not full
            if (fifo_count < DEPTH) begin
                fifo_mem[wr_ptr] <= data_in;
                wr_ptr <= wr_ptr + 1;
                fifo_count <= fifo_count + 1;
            end

            // Example: read when FIFO not empty
            if (fifo_count > 0) begin
                rd_ptr <= rd_ptr + 1;
                fifo_count <= fifo_count - 1;
            end
        end
    end

endmodule

ultrasound/tb/logc/in_buff_tb.v
`timescale 1ns/1ps

module tb_fifo();

    localparam DATA_WIDTH = 16;
    localparam ADDR_WIDTH = 3;
    localparam DEPTH = 1 << ADDR_WIDTH;

    reg clk;
    reg reset;
    reg [DATA_WIDTH-1:0] data_in;
    wire [DATA_WIDTH-1:0] data_out;
    wire [ADDR_WIDTH:0] fifo_count;
    wire [ADDR_WIDTH-1:0] rd_ptr;
    wire [ADDR_WIDTH-1:0] wr_ptr;

    // Instantiate FIFO
    fifo #(
        .DATA_WIDTH(DATA_WIDTH),
        .ADDR_WIDTH(ADDR_WIDTH)
    ) dut (
        .clk(clk),
        .reset(reset),
        .data_in(data_in),
        .data_out(data_out),
        .fifo_count(fifo_count),
        .rd_ptr(rd_ptr),
        .wr_ptr(wr_ptr)
    );

    // Clock generator
    initial clk = 0;
    always #5 clk = ~clk; // 100 MHz

    integer i;

    initial begin
        // Open VCD file for GTKWave
        $dumpfile("fifo_tb.vcd");
        $dumpvars(0, tb_fifo);

        // Reset
        reset = 1;
        data_in = 0;
        #20;
        reset = 0;

        // Write data into FIFO
        for (i = 0; i < DEPTH; i = i + 1) begin
            data_in = i + 16'h100;
            #10; // one clock cycle per write
        end

        // Keep running to show read behavior
        #100;

        // Write again while reading
        for (i = 0; i < DEPTH; i = i + 1) begin
            data_in = i + 16'h200;
            #10;
        end

        #100;

        $finish;
    end

endmodule

ultrasound/fifo_tb.vcd
$date
	Wed Aug 13 16:16:08 2025
$end
$version
	Icarus Verilog
$end
$timescale
	1ps
$end
$scope module tb_fifo $end
$var wire 3 ! wr_ptr [2:0] $end
$var wire 3 " rd_ptr [2:0] $end
$var wire 4 # fifo_count [3:0] $end
$var wire 16 $ data_out [15:0] $end
$var reg 1 % clk $end
$var reg 16 & data_in [15:0] $end
$var reg 1 ' reset $end
$var integer 32 ( i [31:0] $end
$scope module dut $end
$var wire 1 % clk $end
$var wire 16 ) data_in [15:0] $end
$var wire 16 * data_out [15:0] $end
$var wire 1 ' reset $end
$var reg 4 + fifo_count [3:0] $end
$var reg 3 , rd_ptr [2:0] $end
$var reg 3 - wr_ptr [2:0] $end
$upscope $end
$upscope $end
$enddefinitions $end
#0
$dumpvars
b0 -
b0 ,
b0 +
bx *
b0 )
bx (
1'
b0 &
0%
bx $
b0 #
b0 "
b0 !
$end
#5000
1%
#10000
0%
#15000
1%
#20000
0%
b100000000 &
b100000000 )
b0 (
0'
#25000
b1 #
b1 +
b1 !
b1 -
b100000000 $
b100000000 *
1%
#30000
0%
b100000001 &
b100000001 )
b1 (
#35000
b100000001 $
b100000001 *
b1 "
b1 ,
b0 #
b0 +
b10 !
b10 -
1%
#40000
0%
b100000010 &
b100000010 )
b10 (
#45000
b1 #
b1 +
b11 !
b11 -
1%
#50000
0%
b100000011 &
b100000011 )
b11 (
#55000
b100000010 $
b100000010 *
b10 "
b10 ,
b0 #
b0 +
b100 !
b100 -
1%
#60000
0%
b100000100 &
b100000100 )
b100 (
#65000
b1 #
b1 +
b101 !
b101 -
1%
#70000
0%
b100000101 &
b100000101 )
b101 (
#75000
b100000011 $
b100000011 *
b11 "
b11 ,
b0 #
b0 +
b110 !
b110 -
1%
#80000
0%
b100000110 &
b100000110 )
b110 (
#85000
b1 #
b1 +
b111 !
b111 -
1%
#90000
0%
b100000111 &
b100000111 )
b111 (
#95000
b100000100 $
b100000100 *
b100 "
b100 ,
b0 #
b0 +
b0 !
b0 -
1%
#100000
0%
b1000 (
#105000
b1 #
b1 +
b1 !
b1 -
1%
#110000
0%
#115000
b100000101 $
b100000101 *
b101 "
b101 ,
b0 #
b0 +
b10 !
b10 -
1%
#120000
0%
#125000
b1 #
b1 +
b11 !
b11 -
1%
#130000
0%
#135000
b100000110 $
b100000110 *
b110 "
b110 ,
b0 #
b0 +
b100 !
b100 -
1%
#140000
0%
#145000
b1 #
b1 +
b101 !
b101 -
1%
#150000
0%
#155000
b100000111 $
b100000111 *
b111 "
b111 ,
b0 #
b0 +
b110 !
b110 -
1%
#160000
0%
#165000
b1 #
b1 +
b111 !
b111 -
1%
#170000
0%
#175000
b0 "
b0 ,
b0 #
b0 +
b0 !
b0 -
1%
#180000
0%
#185000
b1 #
b1 +
b1 !
b1 -
1%
#190000
0%
#195000
b1 "
b1 ,
b0 #
b0 +
b10 !
b10 -
1%
#200000
0%
b1000000000 &
b1000000000 )
b0 (
#205000
b1 #
b1 +
b11 !
b11 -
1%
#210000
0%
b1000000001 &
b1000000001 )
b1 (
#215000
b1000000000 $
b1000000000 *
b10 "
b10 ,
b0 #
b0 +
b100 !
b100 -
1%
#220000
0%
b1000000010 &
b1000000010 )
b10 (
#225000
b1 #
b1 +
b101 !
b101 -
1%
#230000
0%
b1000000011 &
b1000000011 )
b11 (
#235000
b1000000001 $
b1000000001 *
b11 "
b11 ,
b0 #
b0 +
b110 !
b110 -
1%
#240000
0%
b1000000100 &
b1000000100 )
b100 (
#245000
b1 #
b1 +
b111 !
b111 -
1%
#250000
0%
b1000000101 &
b1000000101 )
b101 (
#255000
b1000000010 $
b1000000010 *
b100 "
b100 ,
b0 #
b0 +
b0 !
b0 -
1%
#260000
0%
b1000000110 &
b1000000110 )
b110 (
#265000
b1 #
b1 +
b1 !
b1 -
1%
#270000
0%
b1000000111 &
b1000000111 )
b111 (
#275000
b1000000011 $
b1000000011 *
b101 "
b101 ,
b0 #
b0 +
b10 !
b10 -
1%
#280000
0%
b1000 (
#285000
b1 #
b1 +
b11 !
b11 -
1%
#290000
0%
#295000
b1000000100 $
b1000000100 *
b110 "
b110 ,
b0 #
b0 +
b100 !
b100 -
1%
#300000
0%
#305000
b1 #
b1 +
b101 !
b101 -
1%
#310000
0%
#315000
b1000000101 $
b1000000101 *
b111 "
b111 ,
b0 #
b0 +
b110 !
b110 -
1%
#320000
0%
#325000
b1 #
b1 +
b111 !
b111 -
1%
#330000
0%
#335000
b0 "
b0 ,
b0 #
b0 +
b0 !
b0 -
b1000000110 $
b1000000110 *
1%
#340000
0%
#345000
b1 #
b1 +
b1 !
b1 -
b1000000111 $
b1000000111 *
1%
#350000
0%
#355000
b1 "
b1 ,
b0 #
b0 +
b10 !
b10 -
1%
#360000
0%
#365000
b1 #
b1 +
b11 !
b11 -
1%
#370000
0%
#375000
b10 "
b10 ,
b0 #
b0 +
b100 !
b100 -
1%
