ultrasound/verilog/logc/postproc.v
module postproc #(
    parameter LOG_WIDTH = 16,
    parameter COMP_WIDTH = LOG_WIDTH / 2
) (
    input clk,
    input reset,
    input in_valid,
    input out_ready,
    input [LOG_WIDTH-1:0] log_in,
    output reg out_valid,
    output reg in_ready,
    output reg [COMP_WIDTH-1:0] comp_out
);

    localparam IDLE = 0, COMPRESS = 1, SEND = 2;
    reg [1:0] state, next_state;

    reg [LOG_WIDTH-1:0] log_reg;
    reg [COMP_WIDTH-1:0] comp_result;

    always @(*) begin
        case (state)
            IDLE: next_state = (in_valid && in_ready) ? COMPRESS : IDLE;
            COMPRESS: next_state = SEND;
            SEND: next_state = (out_ready && out_valid) ? IDLE : SEND;
            default: next_state = IDLE;
        endcase
    end

    always @(posedge clk) begin
        if (reset) begin
            log_reg <= 0;
            comp_result <= 0;
            out_valid <= 0;
            in_ready <= 1;
            state <= IDLE;
        end else begin
            case (state)
                IDLE: begin
                    in_ready <= 1;
                    out_valid <= 0;
                    if (in_valid && in_ready) begin
                        log_reg <= log_in;
                        in_ready <= 0;
                    end
                end
                COMPRESS: begin
                    comp_result <= log_reg[LOG_WIDTH-1 -: COMP_WIDTH];
                end
                SEND: begin
                    comp_out <= comp_result;
                    out_valid <= 1;
                    if (out_ready) begin
                        out_valid <= 0;
                        in_ready <= 1;
                    end
                end
            endcase
            state <= next_state;
        end
    end

endmodule

envelope_detection/hdl/calc_frac.v
module calc_frac #(
    parameter DATA_WIDTH = 16,
    parameter FRAC_WIDTH = 8
)(
    input clk,
    input reset,
    input in_valid,
    input [DATA_WIDTH-1:0] in_data,
    output reg out_valid,
    output reg [FRAC_WIDTH-1:0] out_frac
);

    // Internal registers
    reg [DATA_WIDTH-1:0] rem;  // remainder
    reg [FRAC_WIDTH-1:0] frac;
    reg [4:0] cycle_cnt;       // for multi-cycle shifts
    reg busy;

    always @(posedge clk or posedge reset) begin
        if (reset) begin
            out_valid <= 0;
            out_frac <= 0;
            rem <= 0;
            frac <= 0;
            cycle_cnt <= 0;
            busy <= 0;
        end else begin
            if (in_valid && !busy) begin
                // start calculation
                rem <= in_data;
                frac <= 0;
                cycle_cnt <= FRAC_WIDTH;
                busy <= 1;
                out_valid <= 0;
            end else if (busy) begin
                if (cycle_cnt != 0) begin
                    rem <= rem << 1;               // shift remainder
                    frac <= {frac[FRAC_WIDTH-2:0], rem[DATA_WIDTH-1]}; // extract MSB
                    cycle_cnt <= cycle_cnt - 1;
                end else begin
                    out_frac <= frac;
                    out_valid <= 1;
                    busy <= 0;
                end
            end else begin
                out_valid <= 0;
            end
        end
    end
endmodule

ultrasound/verilog/logc/log_calc.v
module log_calc #(
    parameter NORM_WIDTH = 16,
    parameter LOG_WIDTH = 16,
    parameter FRAC_WIDTH = 8,
    parameter SHIFT_WIDTH = $clog2(NORM_WIDTH)
) (
    input clk,
    input reset,
    input in_valid,
    input out_ready,
    input [NORM_WIDTH-1:0] data_in,
    input [SHIFT_WIDTH-1:0] shift_amt,
    output reg out_valid,
    output reg in_ready,
    output reg [LOG_WIDTH-1:0] log_out
);

    localparam IDLE = 0, CALC_FRAC = 1, COMBINE = 2, SEND = 3;
    reg [1:0] state, next_state;

    reg [NORM_WIDTH-1:0] data_reg;
    reg [SHIFT_WIDTH-1:0] shift_reg;
    reg [FRAC_WIDTH-1:0] frac_part;
    reg [LOG_WIDTH-1:0] log_result;
    reg [SHIFT_WIDTH+FRAC_WIDTH:0] int_part_scaled;

    wire [FRAC_WIDTH-1:0] frac_out;
    wire frac_valid;
    reg frac_in_valid = 0;

    calc_frac #(
        .DATA_WIDTH(NORM_WIDTH),
        .FRAC_WIDTH(FRAC_WIDTH)
    ) frac_inst (
        .clk(clk),
        .reset(reset),
        .in_valid(frac_in_valid),
        .in_data(data_reg),
        .out_valid(frac_valid),
        .out_frac(frac_out)
    );

    always @(*) begin
        case (state)
            IDLE: next_state = (in_valid && in_ready) ? CALC_FRAC : IDLE;
            CALC_FRAC: next_state = (frac_valid) ? COMBINE : CALC_FRAC;
            COMBINE: next_state = SEND;
            SEND: next_state = (out_ready && out_valid) ? IDLE : SEND;
        endcase
    end

    always @(posedge clk ) begin
        if (reset) begin
            state <= IDLE;
            data_reg <= 0;
            shift_reg <= 0;
            frac_part <= 0;
            log_result <= 0;
        end else begin
            case(state)
                IDLE: begin
                    data_reg <= data_in;
                    shift_reg <= shift_amt;
                    out_valid <= 1'b0;
                end

                CALC_FRAC: begin
                    frac_in_valid <= 1'b1;
                    if (frac_valid) begin
                        frac_part <= frac_out;
                        frac_in_valid <= 1'b0;
                    end
                end

                COMBINE: begin
                    int_part_scaled <= shift_reg << FRAC_WIDTH;
                end

                SEND: begin
                    // log_result <= int_part_scaled + frac_part;
                    log_out <= int_part_scaled + frac_part;
                    out_valid <= 1'b1;
                end
            endcase

            state <= next_state;
            in_ready <= (state == IDLE);
        end
    end

endmodule

ultrasound/verilog/logc/preproc.v
module preproc #(
    parameter DATA_WIDTH = 16,
    parameter MIN_THRESHOLD = 1,
    parameter NORM_WIDTH = DATA_WIDTH,
    parameter SHIFT_WIDTH = $clog2(DATA_WIDTH)
) (
    input clk,
    input reset,
    input in_valid,
    input out_ready,
    input [DATA_WIDTH-1:0] data_in,
    output reg out_valid,
    output in_ready,
    output reg [NORM_WIDTH-1:0] data_out,
    output [SHIFT_WIDTH-1:0] shift_amt
);
    reg [DATA_WIDTH-1:0] sample_reg;
    reg [DATA_WIDTH-1:0] zp_reg;
    reg [SHIFT_WIDTH-1:0] msb_index;
    reg [SHIFT_WIDTH-1:0] shift_amt_reg;
    integer i;

    reg found = 0;

    localparam IDLE = 0, CALC_ZP = 1, PROCESS = 2, CALC_SHIFT = 3, LOAD_DOUT = 4, SEND = 5;
    reg [2:0] state, next_state;

    always @(*) begin
        case(state)
            IDLE: next_state = (in_ready && in_valid) ? CALC_ZP : IDLE;
            CALC_ZP: next_state = PROCESS;
            PROCESS: next_state = CALC_SHIFT;
            CALC_SHIFT: next_state = LOAD_DOUT;
            LOAD_DOUT: next_state = SEND;
            SEND: next_state = (out_ready) ? IDLE : SEND;
        endcase
    end

    always @(posedge clk) begin
        if (reset) begin
            sample_reg <= 0;
            out_valid <= 0;
            state <= IDLE;
            found <= 1'b0;
        end else begin
            case(state)
                IDLE: begin
                    sample_reg <= data_in;
                end

                CALC_ZP: begin
                    zp_reg <= (sample_reg == 0) ? MIN_THRESHOLD : sample_reg;
                end

                PROCESS: begin
                    for (i = 0; i <= DATA_WIDTH-1; i = i + 1) begin
                        if (zp_reg[i]) begin
                            if (~found) begin
                                msb_index <= i;
                                found <= 1'b1;
                            end
                        end
                    end
                end

                CALC_SHIFT: begin
                    shift_amt_reg <= (DATA_WIDTH - 1) - msb_index;
                end

                LOAD_DOUT: begin
                    data_out <= zp_reg << shift_amt_reg;                    
                    out_valid <= 1'b1;
                end

                SEND: begin
                    found <= 1'b0;
                    out_valid <= 1'b0;
                end
            endcase

            state <= next_state;
        end
    end

    assign in_ready = !out_valid || out_ready;
    assign shift_amt = shift_amt_reg;

endmodule

ultrasound/verilog/logc/top_logc.v
module top_logc #(
    parameter DATA_WIDTH = 48,
    parameter NORM_WIDTH = DATA_WIDTH,
    parameter SHIFT_WIDTH = $clog2(NORM_WIDTH),
    parameter FRAC_WIDTH = NORM_WIDTH / 2,
    parameter LOG_WIDTH = (SHIFT_WIDTH + FRAC_WIDTH + 1),
    parameter COMP_WIDTH = LOG_WIDTH / 2,
    parameter MIN_THRESHOLD = 0
) (
    input  clk,
    input  reset,
    input  [DATA_WIDTH-1:0] data_in,
    output [COMP_WIDTH-1:0] comp_out
);

    wire                    pre_out_valid;
    wire [NORM_WIDTH-1:0]   pre_data_out;
    wire [SHIFT_WIDTH-1:0]  pre_shift_amt;
    wire                    log_out_valid;
    wire [LOG_WIDTH-1:0]    log_out;
    wire                    pre_in_ready;
    wire                    pre_out_ready;
    wire                    log_in_ready;
    wire                    log_out_ready;

    wire pre_in_valid = 1'b1;

    assign pre_out_ready = log_in_ready;
    assign log_out_ready = 1'b1;

    preproc #(
        .DATA_WIDTH(DATA_WIDTH),
        .NORM_WIDTH(NORM_WIDTH),
        .MIN_THRESHOLD(MIN_THRESHOLD)
    ) preproc_inst (
        .clk(clk),
        .reset(reset),
        .in_valid(pre_in_valid),
        .out_ready(pre_out_ready),
        .data_in(data_in),
        .out_valid(pre_out_valid),
        .in_ready(pre_in_ready),
        .data_out(pre_data_out),
        .shift_amt(pre_shift_amt)
    );

    log_calc #(
        .NORM_WIDTH(NORM_WIDTH),
        .SHIFT_WIDTH(SHIFT_WIDTH),
        .FRAC_WIDTH(FRAC_WIDTH),
        .LOG_WIDTH(LOG_WIDTH)
    ) log_calc_inst (
        .clk(clk),
        .reset(reset),
        .in_valid(pre_out_valid),
        .out_ready(log_out_ready),
        .data_in(pre_data_out),
        .shift_amt(pre_shift_amt),
        .out_valid(log_out_valid),
        .in_ready(log_in_ready),
        .log_out(log_out)
    );

    postproc #(
        .LOG_WIDTH(LOG_WIDTH),
        .COMP_WIDTH(COMP_WIDTH)
    ) postproc_inst (
        .clk(clk),
        .reset(reset),
        .in_valid(log_out_valid),
        .out_ready(1'b1),
        .log_in(log_out),
        .out_valid(),
        .in_ready(log_out_ready),
        .comp_out(comp_out)
    );

endmodule

ultrasound/tb/logc/tb_top_logc.v
`timescale 1ps/1ps

module tb_top_logc;

    parameter DATA_WIDTH = 48;
    parameter COMP_WIDTH = DATA_WIDTH / 2;

    reg clk;
    reg reset;
    reg [DATA_WIDTH-1:0] data_in;
    wire [COMP_WIDTH-1:0] comp_out;

    top_logc #(
        .DATA_WIDTH(DATA_WIDTH),
        .COMP_WIDTH(COMP_WIDTH)
    ) dut (
        .clk(clk),
        .reset(reset),
        .data_in(data_in),
        .comp_out(comp_out)
    );

    initial begin
        clk = 0;
        forever #5 clk = ~clk;
    end

    initial begin
        reset = 1;
        data_in = 0;
        #20;
        reset = 0;
        repeat (30) begin
            @(posedge clk);
            data_in = $random;
        end
        #100;
        $finish;
    end

    initial begin
        $dumpfile("top_logc_tb.vcd");
        $dumpvars(0, tb_top_logc);
    end

endmodule

ultrasound/top_logc_tb.vcd
$date
	Fri Aug 15 22:50:49 2025
$end
$version
	Icarus Verilog
$end
$timescale
	1ps
$end
$scope module tb_top_logc $end
$var wire 24 ! comp_out [23:0] $end
$var reg 1 " clk $end
$var reg 48 # data_in [47:0] $end
$var reg 1 $ reset $end
$scope module dut $end
$var wire 1 " clk $end
$var wire 48 % data_in [47:0] $end
$var wire 1 & log_out_ready $end
$var wire 1 ' pre_in_valid $end
$var wire 1 ( pre_out_ready $end
$var wire 1 $ reset $end
$var wire 6 ) pre_shift_amt [5:0] $end
$var wire 1 * pre_out_valid $end
$var wire 1 + pre_in_ready $end
$var wire 48 , pre_data_out [47:0] $end
$var wire 1 - log_out_valid $end
$var wire 31 . log_out [30:0] $end
$var wire 1 / log_in_ready $end
$var wire 24 0 comp_out [23:0] $end
$scope module log_calc_inst $end
$var wire 1 " clk $end
$var wire 1 & out_ready $end
$var wire 1 $ reset $end
$var wire 6 1 shift_amt [5:0] $end
$var wire 1 * in_valid $end
$var wire 1 2 frac_valid $end
$var wire 24 3 frac_out [23:0] $end
$var wire 48 4 data_in [47:0] $end
$var reg 48 5 data_reg [47:0] $end
$var reg 1 6 frac_in_valid $end
$var reg 24 7 frac_part [23:0] $end
$var reg 1 / in_ready $end
$var reg 31 8 int_part_scaled [30:0] $end
$var reg 31 9 log_out [30:0] $end
$var reg 31 : log_result [30:0] $end
$var reg 2 ; next_state [1:0] $end
$var reg 1 - out_valid $end
$var reg 6 < shift_reg [5:0] $end
$var reg 2 = state [1:0] $end
$scope module frac_inst $end
$var wire 1 " clk $end
$var wire 48 > in_data [47:0] $end
$var wire 1 6 in_valid $end
$var wire 1 $ reset $end
$var reg 1 ? busy $end
$var reg 5 @ cycle_cnt [4:0] $end
$var reg 24 A frac [23:0] $end
$var reg 24 B out_frac [23:0] $end
$var reg 1 2 out_valid $end
$var reg 48 C rem [47:0] $end
$upscope $end
$upscope $end
$scope module postproc_inst $end
$var wire 1 " clk $end
$var wire 1 - in_valid $end
$var wire 31 D log_in [30:0] $end
$var wire 1 E out_ready $end
$var wire 1 $ reset $end
$var reg 24 F comp_out [23:0] $end
$var reg 24 G comp_result [23:0] $end
$var reg 1 H in_ready $end
$var reg 31 I log_reg [30:0] $end
$var reg 2 J next_state [1:0] $end
$var reg 1 K out_valid $end
$var reg 2 L state [1:0] $end
$upscope $end
$scope module preproc_inst $end
$var wire 1 " clk $end
$var wire 48 M data_in [47:0] $end
$var wire 1 + in_ready $end
$var wire 1 ' in_valid $end
$var wire 1 ( out_ready $end
$var wire 1 $ reset $end
$var wire 6 N shift_amt [5:0] $end
$var reg 48 O data_out [47:0] $end
$var reg 1 P found $end
$var reg 6 Q msb_index [5:0] $end
$var reg 3 R next_state [2:0] $end
$var reg 1 * out_valid $end
$var reg 48 S sample_reg [47:0] $end
$var reg 6 T shift_amt_reg [5:0] $end
$var reg 3 U state [2:0] $end
$var reg 48 V zp_reg [47:0] $end
$var integer 32 W i [31:0] $end
$upscope $end
$upscope $end
$upscope $end
$enddefinitions $end
#0
$dumpvars
bx W
bx V
bx U
bx T
bx S
bx R
bx Q
0P
bx O
bx N
b0 M
bx L
xK
b0 J
bx I
xH
bx G
bx F
1E
bx D
b0 C
b0 B
b0 A
b0 @
0?
bx >
bx =
bx <
bx ;
bx :
bx 9
bx 8
bx 7
06
bx 5
bx 4
b0 3
02
bx 1
bx 0
x/
bx .
x-
bx ,
x+
x*
bx )
x(
1'
x&
b0 %
1$
b0 #
0"
bx !
$end
#5
b1 R
1+
b0 ;
b0x J
b0 U
0*
b0 S
b0 :
b0 7
b0 <
b0 5
b0 >
b0 =
b0 L
1&
1H
0K
b0 G
b0 I
1"
#10
0"
#15
1"
#20
0"
0$
#25
b10 R
b0 J
b1 U
b10010000101010011010100100100 S
1(
1/
0-
bx <
bx 5
bx >
b0x L
b10010000101010011010100100100 #
b10010000101010011010100100100 %
b10010000101010011010100100100 M
1"
#30
0"
#35
b11 R
b0 L
b10 U
b10010000101010011010100100100 V
b111111111111111111000000100010010101111010000001 #
b111111111111111111000000100010010101111010000001 %
b111111111111111111000000100010010101111010000001 M
1"
#40
0"
#45
b100 R
b11 U
1P
b11100 Q
b110000 W
b111111111111111110000100100001001101011000001001 #
b111111111111111110000100100001001101011000001001 %
b111111111111111110000100100001001101011000001001 M
1"
#50
0"
#55
b101 R
b100 U
b10011 )
b10011 1
b10011 N
b10011 T
b111111111111111110110001111100000101011001100011 #
b111111111111111110110001111100000101011001100011 %
b111111111111111110110001111100000101011001100011 M
1"
#60
0"
#65
b0 R
b1 ;
b101 U
1*
b100100001010100110101001001000000000000000000000 ,
b100100001010100110101001001000000000000000000000 4
b100100001010100110101001001000000000000000000000 O
b10011 <
b110101110010111101100001101 #
b110101110010111101100001101 %
b110101110010111101100001101 M
1"
#70
0"
#75
b1 R
b1 =
b100100001010100110101001001000000000000000000000 5
b100100001010100110101001001000000000000000000000 >
b0 U
0*
0P
b1000110110111111001100110001101 #
b1000110110111111001100110001101 %
b1000110110111111001100110001101 M
1"
#80
0"
#85
b10 R
b1 U
b111111111111111110110010110000101000010001100101 S
0(
0/
16
b111111111111111110110010110000101000010001100101 #
b111111111111111110110010110000101000010001100101 %
b111111111111111110110010110000101000010001100101 M
1"
#90
0"
#95
b11 R
1?
b11000 @
b100100001010100110101001001000000000000000000000 C
b10 U
b111111111111111110110010110000101000010001100101 V
b111111111111111110001001001101110101001000010010 #
b111111111111111110001001001101110101001000010010 %
b111111111111111110001001001101110101001000010010 M
1"
#100
0"
#105
b100 R
b10111 @
b1 A
b1000010101001101010010010000000000000000000000 C
b11 U
1P
b101111 Q
b110000 W
b111100111110001100000001 #
b111100111110001100000001 %
b111100111110001100000001 M
1"
#110
0"
#115
b101 R
b10110 @
b10 A
b10000101010011010100100100000000000000000000000 C
b100 U
b0 )
b0 1
b0 N
b0 T
b110110101111100110100001101 #
b110110101111100110100001101 %
b110110101111100110100001101 M
1"
#120
0"
#125
0+
b10101 @
b100 A
b100001010100110101001001000000000000000000000000 C
b101 U
1*
b111111111111111110110010110000101000010001100101 ,
b111111111111111110110010110000101000010001100101 4
b111111111111111110110010110000101000010001100101 O
b111011001000111111000101110110 #
b111011001000111111000101110110 %
b111011001000111111000101110110 M
1"
#130
0"
#135
1+
b10100 @
b1001 A
b10101001101010010010000000000000000000000000 C
0*
0P
b11110100011011100110100111101 #
b11110100011011100110100111101 %
b11110100011011100110100111101 M
1"
#140
0"
#145
b10011 @
b10010 A
b101010011010100100100000000000000000000000000 C
b1110110110101000101011111101101 #
b1110110110101000101011111101101 %
b1110110110101000101011111101101 M
1"
#150
0"
#155
b10010 @
b100100 A
b1010100110101001001000000000000000000000000000 C
b1000110001011011111011110001100 #
b1000110001011011111011110001100 %
b1000110001011011111011110001100 M
1"
#160
0"
#165
b10001 @
b1001000 A
b10101001101010010010000000000000000000000000000 C
b1111100111111011110100111111001 #
b1111100111111011110100111111001 %
b1111100111111011110100111111001 M
1"
#170
0"
#175
b10000 @
b10010000 A
b101010011010100100100000000000000000000000000000 C
b111111111111111111100011001101110010010011000110 #
b111111111111111111100011001101110010010011000110 %
b111111111111111111100011001101110010010011000110 M
1"
#180
0"
#185
b1111 @
b100100001 A
b10100110101001001000000000000000000000000000000 C
b111111111111111111100010111101111000010011000101 #
b111111111111111111100010111101111000010011000101 %
b111111111111111111100010111101111000010011000101 M
1"
#190
0"
#195
b1110 @
b1001000010 A
b101001101010010010000000000000000000000000000000 C
b111111111111111111010101000100111101001010101010 #
b111111111111111111010101000100111101001010101010 %
b111111111111111111010101000100111101001010101010 M
1"
#200
0"
#205
b1101 @
b10010000101 A
b10011010100100100000000000000000000000000000000 C
b1110010101011111111011111100101 #
b1110010101011111111011111100101 %
b1110010101011111111011111100101 M
1"
#210
0"
#215
b1100 @
b100100001010 A
b100110101001001000000000000000000000000000000000 C
b111111111111111110111011110100100111001001110111 #
b111111111111111110111011110100100111001001110111 %
b111111111111111110111011110100100111001001110111 M
1"
#220
0"
#225
b1011 @
b1001000010101 A
b1101010010010000000000000000000000000000000000 C
b111111111111111110001001001100101101011000010010 #
b111111111111111110001001001100101101011000010010 %
b111111111111111110001001001100101101011000010010 M
1"
#230
0"
#235
b1010 @
b10010000101010 A
b11010100100100000000000000000000000000000000000 C
b1000111111011001101101110001111 #
b1000111111011001101101110001111 %
b1000111111011001101101110001111 M
1"
#240
0"
#245
b1001 @
b100100001010100 A
b110101001001000000000000000000000000000000000000 C
b1111001001100000110100111110010 #
b1111001001100000110100111110010 %
b1111001001100000110100111110010 M
1"
#250
0"
#255
b1000 @
b1001000010101001 A
b101010010010000000000000000000000000000000000000 C
b111111111111111111100111011101101001011011001110 #
b111111111111111111100111011101101001011011001110 %
b111111111111111111100111011101101001011011001110 M
1"
#260
0"
#265
b111 @
b10010000101010011 A
b10100100100000000000000000000000000000000000000 C
b111111111111111111110100000000000111101011101000 #
b111111111111111111110100000000000111101011101000 %
b111111111111111111110100000000000111101011101000 M
1"
#270
0"
#275
b110 @
b100100001010100110 A
b101001001000000000000000000000000000000000000000 C
b111111111111111111100010110010100100111011000101 #
b111111111111111111100010110010100100111011000101 %
b111111111111111111100010110010100100111011000101 M
1"
#280
0"
#285
b101 @
b1001000010101001101 A
b10010010000000000000000000000000000000000000000 C
b101110010110000100100101011100 #
b101110010110000100100101011100 %
b101110010110000100100101011100 M
1"
#290
0"
#295
b100 @
b10010000101010011010 A
b100100100000000000000000000000000000000000000000 C
b111111111111111111011110100011100010100010111101 #
b111111111111111111011110100011100010100010111101 %
b111111111111111111011110100011100010100010111101 M
1"
#300
0"
#305
b11 @
b100100001010100110101 A
b1001000000000000000000000000000000000000000000 C
b111111111111111110010110101010110101100000101101 #
b111111111111111110010110101010110101100000101101 %
b111111111111111110010110101010110101100000101101 M
1"
#310
0"
#315
b10 @
b1001000010101001101010 A
b10010000000000000000000000000000000000000000000 C
b111111111111111110110010101001110010011001100101 #
b111111111111111110110010101001110010011001100101 %
b111111111111111110110010101001110010011001100101 M
1"
#320
0"
#325
b1 @
b10010000101010011010100 A
b100100000000000000000000000000000000000000000000 C
1"
#330
0"
#335
b0 @
b100100001010100110101001 A
b1000000000000000000000000000000000000000000000 C
1"
#340
0"
#345
b10 ;
0?
12
b100100001010100110101001 3
b100100001010100110101001 B
1"
#350
0"
#355
b11 ;
02
1?
b11000 @
b0 A
b100100001010100110101001001000000000000000000000 C
b10 =
06
b100100001010100110101001 7
1"
#360
0"
#365
b10111 @
b1 A
b1000010101001101010010010000000000000000000000 C
b11 =
b10011000000000000000000000000 8
1"
#370
0"
#375
b0 ;
b1 J
b10110 @
b10 A
b10000101010011010100100100000000000000000000000 C
1-
b10011100100001010100110101001 .
b10011100100001010100110101001 9
b10011100100001010100110101001 D
1"
#380
0"
#385
b10 J
b10101 @
b100 A
b100001010100110101001001000000000000000000000000 C
b0 =
b1 L
x&
0H
b10011100100001010100110101001 I
1"
#390
0"
#395
b0 R
b10100 @
b1001 A
b10101001101010010010000000000000000000000000 C
b10 L
b1001110010000101010011 G
1(
1/
0-
b0 <
b111111111111111110110010110000101000010001100101 5
b111111111111111110110010110000101000010001100101 >
1"
#400
0"
#405
b1 R
b10011 @
b10010 A
b101010011010100100100000000000000000000000000 C
b0 U
1&
1H
0K
b1001110010000101010011 !
b1001110010000101010011 0
b1001110010000101010011 F
1"
#410
0"
#415
b10 R
b10010 @
b100100 A
b1010100110101001001000000000000000000000000000 C
0K
b1 U
b111111111111111110110010101001110010011001100101 S
1"
