ultrasound/verilog/logc/postproc.v
module postproc #(
    parameter LOG_WIDTH = 16,
    parameter COMP_WIDTH = LOG_WIDTH / 2
) (
    input clk,
    input reset,
    input in_valid,
    input out_ready,
    input [LOG_WIDTH-1:0] log_in,
    output reg out_valid,
    output reg in_ready,
    output reg [COMP_WIDTH-1:0] comp_out
);

    localparam IDLE = 0, COMPRESS = 1, SEND = 2;
    reg [1:0] state, next_state;

    reg [LOG_WIDTH-1:0] log_reg;
    reg [COMP_WIDTH-1:0] comp_result;

    always @(*) begin
        case (state)
            IDLE: next_state = (in_valid && in_ready) ? COMPRESS : IDLE;
            COMPRESS: next_state = SEND;
            SEND: next_state = (out_ready && out_valid) ? IDLE : SEND;
            default: next_state = IDLE;
        endcase
    end

    always @(posedge clk) begin
        if (reset) begin
            log_reg <= 0;
            comp_result <= 0;
            out_valid <= 0;
            in_ready <= 1;
            state <= IDLE;
        end else begin
            case (state)
                IDLE: begin
                    in_ready <= 1;
                    out_valid <= 0;
                    if (in_valid && in_ready) begin
                        log_reg <= log_in;
                        in_ready <= 0;
                    end
                end
                COMPRESS: begin
                    comp_result <= log_reg[LOG_WIDTH-1 -: COMP_WIDTH];
                end
                SEND: begin
                    comp_out <= comp_result;
                    out_valid <= 1;
                    if (out_ready) begin
                        out_valid <= 0;
                        in_ready <= 1;
                    end
                end
            endcase
            state <= next_state;
        end
    end

endmodule

envelope_detection/hdl/calc_frac.v
module calc_frac #(
    parameter DATA_WIDTH = 16,
    parameter FRAC_WIDTH = 8
)(
    input clk,
    input reset,
    input in_valid,
    input [DATA_WIDTH-1:0] in_data,
    output reg out_valid,
    output reg [FRAC_WIDTH-1:0] out_frac
);

    // Internal registers
    reg [DATA_WIDTH-1:0] rem;  // remainder
    reg [FRAC_WIDTH-1:0] frac;
    reg [4:0] cycle_cnt;       // for multi-cycle shifts
    reg busy;

    always @(posedge clk or posedge reset) begin
        if (reset) begin
            out_valid <= 0;
            out_frac <= 0;
            rem <= 0;
            frac <= 0;
            cycle_cnt <= 0;
            busy <= 0;
        end else begin
            if (in_valid && !busy) begin
                // start calculation
                rem <= in_data;
                frac <= 0;
                cycle_cnt <= FRAC_WIDTH;
                busy <= 1;
                out_valid <= 0;
            end else if (busy) begin
                if (cycle_cnt != 0) begin
                    rem <= rem << 1;               // shift remainder
                    frac <= {frac[FRAC_WIDTH-2:0], rem[DATA_WIDTH-1]}; // extract MSB
                    cycle_cnt <= cycle_cnt - 1;
                end else begin
                    out_frac <= frac;
                    out_valid <= 1;
                    busy <= 0;
                end
            end else begin
                out_valid <= 0;
            end
        end
    end
endmodule

ultrasound/verilog/logc/log_calc.v
module log_calc #(
    parameter NORM_WIDTH = 16,
    parameter LOG_WIDTH = 16,
    parameter FRAC_WIDTH = 8,
    parameter SHIFT_WIDTH = $clog2(NORM_WIDTH)
) (
    input clk,
    input reset,
    input in_valid,
    input out_ready,
    input [NORM_WIDTH-1:0] data_in,
    input [SHIFT_WIDTH-1:0] shift_amt,
    output reg out_valid,
    output reg in_ready,
    output reg [LOG_WIDTH-1:0] log_out
);

    localparam IDLE = 0, CALC_FRAC = 1, COMBINE = 2, SEND = 3;
    reg [1:0] state, next_state;

    reg [NORM_WIDTH-1:0] data_reg;
    reg [SHIFT_WIDTH-1:0] shift_reg;
    reg [FRAC_WIDTH-1:0] frac_part;
    reg [LOG_WIDTH-1:0] log_result;
    reg [SHIFT_WIDTH+FRAC_WIDTH:0] int_part_scaled;

    wire [FRAC_WIDTH-1:0] frac_out;
    wire frac_valid;
    reg frac_in_valid;

    calc_frac #(
        .DATA_WIDTH(NORM_WIDTH),
        .FRAC_WIDTH(FRAC_WIDTH)
    ) frac_inst (
        .clk(clk),
        .reset(reset),
        .in_valid(frac_in_valid),
        .in_data(data_reg),
        .out_valid(frac_valid),
        .out_frac(frac_out)
    );

    always @(*) begin
        case (state)
            IDLE: next_state = (in_valid && in_ready) ? CALC_FRAC : IDLE;
            CALC_FRAC: next_state = (frac_valid) ? COMBINE : CALC_FRAC;
            COMBINE: next_state = SEND;
            SEND: next_state = (out_ready && out_valid) ? IDLE : SEND;
        endcase
    end

    always @(posedge clk ) begin
        if (reset) begin
            data_reg <= 0;
            shift_reg <= 0;
            frac_part <= 0;
            log_result <= 0;
        end else begin
            case(state)
                IDLE: begin
                    data_reg <= data_in;
                    shift_reg <= shift_amt;
                    out_valid <= 1'b0;
                end

                CALC_FRAC: begin
                    frac_in_valid <= 1'b1;
                    if (frac_valid) begin
                        frac_part <= frac_out;
                        frac_in_valid <= 1'b0;
                    end
                end

                COMBINE: begin
                    int_part_scaled <= shift_amt << FRAC_WIDTH;
                    log_result <= int_part_scaled + frac_part;
                end

                SEND: begin
                    log_out <= log_result;
                    out_valid <= 1'b1;
                end
            endcase

            state <= next_state;
            in_ready <= (state == IDLE);
        end
    end

endmodule

ultrasound/verilog/logc/preproc.v
module preproc #(
    parameter DATA_WIDTH = 16,
    parameter MIN_THRESHOLD = 1,
    parameter NORM_WIDTH = DATA_WIDTH,
    parameter SHIFT_WIDTH = $clog2(DATA_WIDTH)
) (
    input clk,
    input reset,
    input in_valid,
    input out_ready,
    input [DATA_WIDTH-1:0] data_in,
    output reg out_valid,
    output in_ready,
    output reg [NORM_WIDTH-1:0] data_out,
    output [SHIFT_WIDTH-1:0] shift_amt
);
    reg [DATA_WIDTH-1:0] sample_reg;
    reg [DATA_WIDTH-1:0] zp_reg;
    reg [SHIFT_WIDTH-1:0] msb_index;
    reg [SHIFT_WIDTH-1:0] shift_amt_reg;
    integer i;

    reg found = 0;

    localparam IDLE = 0, LOAD_DATA = 1, CALC_ZP = 2, PROCESS = 3, CALC_SHIFT = 4, LOAD_DOUT = 5, SEND = 6;
    reg [2:0] state, next_state;

    always @(*) begin
        case(state)
            IDLE: next_state = (in_ready && in_valid) ? CALC_ZP : IDLE;
            LOAD_DATA: next_state = CALC_ZP;
            CALC_ZP: next_state = PROCESS;
            PROCESS: next_state = CALC_SHIFT;
            CALC_SHIFT: next_state = LOAD_DOUT;
            LOAD_DOUT: next_state = SEND;
            SEND: next_state = (out_ready) ? IDLE : SEND;
        endcase
    end

    always @(posedge clk) begin
        if (reset) begin
            sample_reg <= 0;
            out_valid <= 0;
            state <= IDLE;
            found <= 1'b0;
        end else begin
            case(state)
                IDLE: begin
                    sample_reg <= data_in;
                end

                LOAD_DATA: begin
                    sample_reg <= data_in;
                end

                CALC_ZP: begin
                    zp_reg <= (sample_reg == 0) ? MIN_THRESHOLD : sample_reg;
                end

                PROCESS: begin
                    for (i = 0; i <= DATA_WIDTH-1; i = i + 1) begin
                        if (zp_reg[i]) begin
                            if (~found) begin
                                msb_index <= i;
                                found <= 1'b1;
                            end
                        end
                    end
                end

                CALC_SHIFT: begin
                    shift_amt_reg <= (DATA_WIDTH - 1) - msb_index;
                end

                LOAD_DOUT: begin
                    data_out <= zp_reg << shift_amt_reg;                    
                    out_valid <= 1'b1;
                end

                SEND: begin
                    found <= 1'b0;
                    out_valid <= 1'b0;
                end
            endcase

            state <= next_state;
        end
    end

    // assign in_ready = !out_valid || out_ready;
    assign in_ready = (state == IDLE);
    assign shift_amt = shift_amt_reg;

endmodule

ultrasound/verilog/logc/top_logc.v
module top_logc #(
    parameter DATA_WIDTH = 48,
    parameter NORM_WIDTH = DATA_WIDTH,
    parameter SHIFT_WIDTH = $clog2(NORM_WIDTH),
    parameter FRAC_WIDTH = NORM_WIDTH / 2,
    parameter LOG_WIDTH = (SHIFT_WIDTH + FRAC_WIDTH + 1),
    parameter COMP_WIDTH = LOG_WIDTH / 2,
    parameter MIN_THRESHOLD = 0
) (
    input  clk,
    input  reset,
    input  [DATA_WIDTH-1:0] data_in,
    input fifo_out_valid,
    output pre_in_ready,
    output [COMP_WIDTH-1:0] comp_out
);

    wire                    pre_out_valid;
    wire [NORM_WIDTH-1:0]   pre_data_out;
    wire [SHIFT_WIDTH-1:0]  pre_shift_amt;
    wire                    log_out_valid;
    wire [LOG_WIDTH-1:0]    log_out;
    // wire                    pre_in_ready;
    wire                    pre_out_ready;
    wire                    log_in_ready;
    wire                    log_out_ready;

    // wire fifo_out_valid = 1'b1;

    assign pre_out_ready = log_in_ready;
    assign log_out_ready = 1'b1;

    preproc #(
        .DATA_WIDTH(DATA_WIDTH),
        .NORM_WIDTH(NORM_WIDTH),
        .MIN_THRESHOLD(MIN_THRESHOLD)
    ) preproc_inst (
        .clk(clk),
        .reset(reset),
        .in_valid(fifo_out_valid),
        .out_ready(pre_out_ready),
        .data_in(data_in),
        .out_valid(pre_out_valid),
        .in_ready(pre_in_ready),
        .data_out(pre_data_out),
        .shift_amt(pre_shift_amt)
    );

    log_calc #(
        .NORM_WIDTH(NORM_WIDTH),
        .SHIFT_WIDTH(SHIFT_WIDTH),
        .FRAC_WIDTH(FRAC_WIDTH),
        .LOG_WIDTH(LOG_WIDTH)
    ) log_calc_inst (
        .clk(clk),
        .reset(reset),
        .in_valid(pre_out_valid),
        .out_ready(log_out_ready),
        .data_in(pre_data_out),
        .shift_amt(pre_shift_amt),
        .out_valid(log_out_valid),
        .in_ready(log_in_ready),
        .log_out(log_out)
    );

    postproc #(
        .LOG_WIDTH(LOG_WIDTH),
        .COMP_WIDTH(COMP_WIDTH)
    ) postproc_inst (
        .clk(clk),
        .reset(reset),
        .in_valid(log_out_valid),
        .out_ready(1'b1),
        .log_in(log_out),
        .out_valid(),
        .in_ready(log_out_ready),
        .comp_out(comp_out)
    );

endmodule

envelope_detection/hdl/fifo.v
module fifo #(
    parameter DATA_WIDTH = 16
) (
    input clk,
    input reset,
    input [DATA_WIDTH-1:0] data_in,
    input wr_en,
    input rd_en,

    output wire [DATA_WIDTH-1:0] data_out,
    output wire [ADDR_WIDTH:0]   fifo_count,
    output wire out_valid
);

    localparam DEPTH = 30;
    localparam ADDR_WIDTH = $clog2(DEPTH);

    reg [DATA_WIDTH-1:0] fifo_mem [0:DEPTH-1];

    reg [ADDR_WIDTH:0] wr_ptr_ext;
    reg [ADDR_WIDTH:0] rd_ptr_ext;

    wire [ADDR_WIDTH-1:0] wr_ptr;
    wire [ADDR_WIDTH-1:0] rd_ptr;
    wire full;
    wire empty;

    assign wr_ptr = wr_ptr_ext[ADDR_WIDTH-1:0];
    assign rd_ptr = rd_ptr_ext[ADDR_WIDTH-1:0];

    assign data_out = fifo_mem[rd_ptr];

    assign empty = (wr_ptr_ext == rd_ptr_ext);

    assign full = ((wr_ptr_ext[ADDR_WIDTH] != rd_ptr_ext[ADDR_WIDTH]) && (wr_ptr == rd_ptr));

    assign out_valid = !empty;

    assign fifo_count = wr_ptr_ext - rd_ptr_ext;

    always @(posedge clk or posedge reset) begin
        if (reset) begin
            wr_ptr_ext <= 0;
            rd_ptr_ext <= 0;
        end else begin
            if (wr_en && !full) begin
                fifo_mem[wr_ptr] <= data_in;
                wr_ptr_ext <= wr_ptr_ext + 1;
            end

            if (rd_en && !empty) begin
                rd_ptr_ext <= rd_ptr_ext + 1;
            end
        end
    end

endmodule

ultrasound/tb/logc/tb_top_logc.v
`timescale 1ps/1ps

module tb_top_logc;

    parameter DATA_WIDTH = 48;
    parameter DEPTH = 30;
    localparam ADDR_WIDTH = $clog2(DEPTH);
    parameter COMP_WIDTH = DATA_WIDTH / 2;

    reg clk;
    reg reset;
    reg [DATA_WIDTH-1:0] data_in;
    wire [DATA_WIDTH-1:0] data_out;
    wire [ADDR_WIDTH:0] fifo_count;
    wire [ADDR_WIDTH-1:0] rd_ptr;
    wire [ADDR_WIDTH-1:0] wr_ptr;
    wire [COMP_WIDTH-1:0] comp_out;
    wire pir;
    wire fifo_out_valid;

    fifo # (
        DATA_WIDTH,
    ) fifo_inst (
        .clk(clk),
        .reset(reset),
        .data_in(data_in),
        .rd_en(pir),
        .wr_en(1'b1),
        .data_out(data_out),
        .fifo_count(fifo_count),
        .out_valid(fifo_out_valid)
    );

    top_logc #(
        .DATA_WIDTH(DATA_WIDTH),
        .COMP_WIDTH(COMP_WIDTH)
    ) dut (
        .clk(clk),
        .reset(reset),
        .data_in(data_out),
        .pre_in_ready(pir),
        .fifo_out_valid(fifo_out_valid),
        .comp_out(comp_out)
    );

    initial begin
        clk = 0;
        forever #5 clk = ~clk;
    end

    initial begin
        reset = 1;
        data_in = 0;
        #20;
        reset = 0;
        repeat (30) begin
            @(posedge clk);
            data_in = $random;
        end
        #100;
        $finish;
    end

    initial begin
        $dumpfile("top_logc_tb.vcd");
        $dumpvars(0, tb_top_logc);
    end

endmodule

ultrasound/vcb/top_logc_tb.vcd
$date
	Sat Aug 16 16:32:17 2025
$end
$version
	Icarus Verilog
$end
$timescale
	1ps
$end
$scope module tb_top_logc $end
$var wire 1 ! pir $end
$var wire 1 " fifo_out_valid $end
$var wire 6 # fifo_count [5:0] $end
$var wire 48 $ data_out [47:0] $end
$var wire 24 % comp_out [23:0] $end
$var reg 1 & clk $end
$var reg 48 ' data_in [47:0] $end
$var reg 1 ( reset $end
$scope module dut $end
$var wire 1 & clk $end
$var wire 1 ) log_out_ready $end
$var wire 1 * pre_out_ready $end
$var wire 1 ( reset $end
$var wire 6 + pre_shift_amt [5:0] $end
$var wire 1 , pre_out_valid $end
$var wire 1 ! pre_in_ready $end
$var wire 48 - pre_data_out [47:0] $end
$var wire 1 . log_out_valid $end
$var wire 31 / log_out [30:0] $end
$var wire 1 0 log_in_ready $end
$var wire 1 " fifo_out_valid $end
$var wire 48 1 data_in [47:0] $end
$var wire 24 2 comp_out [23:0] $end
$scope module log_calc_inst $end
$var wire 1 & clk $end
$var wire 1 ) out_ready $end
$var wire 1 ( reset $end
$var wire 6 3 shift_amt [5:0] $end
$var wire 1 , in_valid $end
$var wire 1 4 frac_valid $end
$var wire 24 5 frac_out [23:0] $end
$var wire 48 6 data_in [47:0] $end
$var reg 48 7 data_reg [47:0] $end
$var reg 1 8 frac_in_valid $end
$var reg 24 9 frac_part [23:0] $end
$var reg 1 0 in_ready $end
$var reg 31 : int_part_scaled [30:0] $end
$var reg 31 ; log_out [30:0] $end
$var reg 31 < log_result [30:0] $end
$var reg 2 = next_state [1:0] $end
$var reg 1 . out_valid $end
$var reg 6 > shift_reg [5:0] $end
$var reg 2 ? state [1:0] $end
$scope module frac_inst $end
$var wire 1 & clk $end
$var wire 48 @ in_data [47:0] $end
$var wire 1 8 in_valid $end
$var wire 1 ( reset $end
$var reg 1 A busy $end
$var reg 5 B cycle_cnt [4:0] $end
$var reg 24 C frac [23:0] $end
$var reg 24 D out_frac [23:0] $end
$var reg 1 4 out_valid $end
$var reg 48 E rem [47:0] $end
$upscope $end
$upscope $end
$scope module postproc_inst $end
$var wire 1 & clk $end
$var wire 1 . in_valid $end
$var wire 31 F log_in [30:0] $end
$var wire 1 G out_ready $end
$var wire 1 ( reset $end
$var reg 24 H comp_out [23:0] $end
$var reg 24 I comp_result [23:0] $end
$var reg 1 J in_ready $end
$var reg 31 K log_reg [30:0] $end
$var reg 2 L next_state [1:0] $end
$var reg 1 M out_valid $end
$var reg 2 N state [1:0] $end
$upscope $end
$scope module preproc_inst $end
$var wire 1 & clk $end
$var wire 1 * out_ready $end
$var wire 1 ( reset $end
$var wire 6 O shift_amt [5:0] $end
$var wire 1 " in_valid $end
$var wire 1 ! in_ready $end
$var wire 48 P data_in [47:0] $end
$var reg 48 Q data_out [47:0] $end
$var reg 1 R found $end
$var reg 6 S msb_index [5:0] $end
$var reg 3 T next_state [2:0] $end
$var reg 1 , out_valid $end
$var reg 48 U sample_reg [47:0] $end
$var reg 6 V shift_amt_reg [5:0] $end
$var reg 3 W state [2:0] $end
$var reg 48 X zp_reg [47:0] $end
$var integer 32 Y i [31:0] $end
$upscope $end
$upscope $end
$scope module fifo_inst $end
$var wire 1 & clk $end
$var wire 48 Z data_in [47:0] $end
$var wire 48 [ data_out [47:0] $end
$var wire 1 \ full $end
$var wire 1 ! rd_en $end
$var wire 1 ( reset $end
$var wire 1 ] wr_en $end
$var wire 5 ^ wr_ptr [4:0] $end
$var wire 5 _ rd_ptr [4:0] $end
$var wire 1 " out_valid $end
$var wire 6 ` fifo_count [5:0] $end
$var wire 1 a empty $end
$var reg 6 b rd_ptr_ext [5:0] $end
$var reg 6 c wr_ptr_ext [5:0] $end
$upscope $end
$upscope $end
$enddefinitions $end
#0
$dumpvars
b0 c
b0 b
1a
b0 `
b0 _
b0 ^
1]
0\
bx [
b0 Z
bx Y
bx X
bx W
bx V
bx U
bx T
bx S
0R
bx Q
bx P
bx O
bx N
xM
b0 L
bx K
xJ
bx I
bx H
1G
bx F
b0 E
b0 D
b0 C
b0 B
0A
bx @
bx ?
bx >
bx =
bx <
bx ;
bx :
bx 9
08
bx 7
bx 6
b0 5
04
bx 3
bx 2
bx 1
x0
bx /
x.
bx -
x,
bx +
x*
x)
1(
b0 '
0&
bx %
bx $
b0 #
0"
x!
$end
#5
b0 T
b0 =
b0x L
1!
b0 W
0,
b0 U
b0 <
b0 9
b0 >
b0 7
b0 @
b0 ?
b0 N
1)
1J
0M
b0 I
b0 K
1&
#10
0&
#15
1&
#20
0&
0(
#25
b1 ^
b10 T
b0 L
1"
0a
b1 #
b1 `
b1 c
b10010000101010011010100100100 $
b10010000101010011010100100100 1
b10010000101010011010100100100 P
b10010000101010011010100100100 [
bx U
1*
10
0.
bx >
bx 7
bx @
b0x N
b10010000101010011010100100100 '
b10010000101010011010100100100 Z
1&
#30
0&
#35
b111111111111111111000000100010010101111010000001 $
b111111111111111111000000100010010101111010000001 1
b111111111111111111000000100010010101111010000001 P
b111111111111111111000000100010010101111010000001 [
b1 _
b10 ^
b11 T
b1 b
b1 #
b1 `
b10 c
b0 N
0!
b10 W
b10010000101010011010100100100 U
b111111111111111111000000100010010101111010000001 '
b111111111111111111000000100010010101111010000001 Z
1&
#40
0&
#45
b11 ^
b100 T
b10 #
b10 `
b11 c
b11 W
b10010000101010011010100100100 X
b111111111111111110000100100001001101011000001001 '
b111111111111111110000100100001001101011000001001 Z
1&
#50
0&
#55
b100 ^
b101 T
b11 #
b11 `
b100 c
b100 W
1R
b11100 S
b111111111111111110110001111100000101011001100011 '
b111111111111111110110001111100000101011001100011 Z
b110000 Y
1&
#60
0&
#65
b101 ^
b110 T
b100 #
b100 `
b101 c
b101 W
b10011 +
b10011 3
b10011 O
b10011 V
b110101110010111101100001101 '
b110101110010111101100001101 Z
1&
#70
0&
#75
b110 ^
b0 T
b1 =
b101 #
b101 `
b110 c
b10011 >
b110 W
1,
b100100001010100110101001001000000000000000000000 -
b100100001010100110101001001000000000000000000000 6
b100100001010100110101001001000000000000000000000 Q
b1000110110111111001100110001101 '
b1000110110111111001100110001101 Z
1&
#80
0&
#85
b111 ^
b10 T
b110 #
b110 `
b111 c
1!
b0 W
0,
0R
b1 ?
b100100001010100110101001001000000000000000000000 7
b100100001010100110101001001000000000000000000000 @
b111111111111111110110010110000101000010001100101 '
b111111111111111110110010110000101000010001100101 Z
1&
#90
0&
#95
b111111111111111110000100100001001101011000001001 $
b111111111111111110000100100001001101011000001001 1
b111111111111111110000100100001001101011000001001 P
b111111111111111110000100100001001101011000001001 [
b10 _
b1000 ^
b11 T
b10 b
b110 #
b110 `
b1000 c
0*
00
18
0!
b10 W
b111111111111111111000000100010010101111010000001 U
b111111111111111110001001001101110101001000010010 '
b111111111111111110001001001101110101001000010010 Z
1&
#100
0&
#105
b1001 ^
b100 T
1A
b11000 B
b100100001010100110101001001000000000000000000000 E
b111 #
b111 `
b1001 c
b11 W
b111111111111111111000000100010010101111010000001 X
b111100111110001100000001 '
b111100111110001100000001 Z
1&
#110
0&
#115
b1010 ^
b101 T
b1000 #
b1000 `
b1010 c
b10111 B
b1 C
b1000010101001101010010010000000000000000000000 E
b100 W
1R
b101111 S
b110110101111100110100001101 '
b110110101111100110100001101 Z
b110000 Y
1&
#120
0&
#125
b1011 ^
b110 T
b10110 B
b10 C
b10000101010011010100100100000000000000000000000 E
b1001 #
b1001 `
b1011 c
b101 W
b0 +
b0 3
b0 O
b0 V
b111011001000111111000101110110 '
b111011001000111111000101110110 Z
1&
#130
0&
#135
b1100 ^
b1010 #
b1010 `
b1100 c
b10101 B
b100 C
b100001010100110101001001000000000000000000000000 E
b110 W
1,
b111111111111111111000000100010010101111010000001 -
b111111111111111111000000100010010101111010000001 6
b111111111111111111000000100010010101111010000001 Q
b11110100011011100110100111101 '
b11110100011011100110100111101 Z
1&
#140
0&
#145
b1101 ^
b10100 B
b1001 C
b10101001101010010010000000000000000000000000 E
b1011 #
b1011 `
b1101 c
0,
0R
b1110110110101000101011111101101 '
b1110110110101000101011111101101 Z
1&
#150
0&
#155
b1110 ^
b1100 #
b1100 `
b1110 c
b10011 B
b10010 C
b101010011010100100100000000000000000000000000 E
b1000110001011011111011110001100 '
b1000110001011011111011110001100 Z
1&
#160
0&
#165
b1111 ^
b10010 B
b100100 C
b1010100110101001001000000000000000000000000000 E
b1101 #
b1101 `
b1111 c
b1111100111111011110100111111001 '
b1111100111111011110100111111001 Z
1&
#170
0&
#175
b10000 ^
b1110 #
b1110 `
b10000 c
b10001 B
b1001000 C
b10101001101010010010000000000000000000000000000 E
b111111111111111111100011001101110010010011000110 '
b111111111111111111100011001101110010010011000110 Z
1&
#180
0&
#185
b10001 ^
b10000 B
b10010000 C
b101010011010100100100000000000000000000000000000 E
b1111 #
b1111 `
b10001 c
b111111111111111111100010111101111000010011000101 '
b111111111111111111100010111101111000010011000101 Z
1&
#190
0&
#195
b10010 ^
b10000 #
b10000 `
b10010 c
b1111 B
b100100001 C
b10100110101001001000000000000000000000000000000 E
b111111111111111111010101000100111101001010101010 '
b111111111111111111010101000100111101001010101010 Z
1&
#200
0&
#205
b10011 ^
b1110 B
b1001000010 C
b101001101010010010000000000000000000000000000000 E
b10001 #
b10001 `
b10011 c
b1110010101011111111011111100101 '
b1110010101011111111011111100101 Z
1&
#210
0&
#215
b10100 ^
b10010 #
b10010 `
b10100 c
b1101 B
b10010000101 C
b10011010100100100000000000000000000000000000000 E
b111111111111111110111011110100100111001001110111 '
b111111111111111110111011110100100111001001110111 Z
1&
#220
0&
#225
b10101 ^
b1100 B
b100100001010 C
b100110101001001000000000000000000000000000000000 E
b10011 #
b10011 `
b10101 c
b111111111111111110001001001100101101011000010010 '
b111111111111111110001001001100101101011000010010 Z
1&
#230
0&
#235
b10110 ^
b10100 #
b10100 `
b10110 c
b1011 B
b1001000010101 C
b1101010010010000000000000000000000000000000000 E
b1000111111011001101101110001111 '
b1000111111011001101101110001111 Z
1&
#240
0&
#245
b10111 ^
b1010 B
b10010000101010 C
b11010100100100000000000000000000000000000000000 E
b10101 #
b10101 `
b10111 c
b1111001001100000110100111110010 '
b1111001001100000110100111110010 Z
1&
#250
0&
#255
b11000 ^
b10110 #
b10110 `
b11000 c
b1001 B
b100100001010100 C
b110101001001000000000000000000000000000000000000 E
b111111111111111111100111011101101001011011001110 '
b111111111111111111100111011101101001011011001110 Z
1&
#260
0&
#265
b11001 ^
b1000 B
b1001000010101001 C
b101010010010000000000000000000000000000000000000 E
b10111 #
b10111 `
b11001 c
b111111111111111111110100000000000111101011101000 '
b111111111111111111110100000000000111101011101000 Z
1&
#270
0&
#275
b11010 ^
b11000 #
b11000 `
b11010 c
b111 B
b10010000101010011 C
b10100100100000000000000000000000000000000000000 E
b111111111111111111100010110010100100111011000101 '
b111111111111111111100010110010100100111011000101 Z
1&
#280
0&
#285
b11011 ^
b110 B
b100100001010100110 C
b101001001000000000000000000000000000000000000000 E
b11001 #
b11001 `
b11011 c
b101110010110000100100101011100 '
b101110010110000100100101011100 Z
1&
#290
0&
#295
b11100 ^
b11010 #
b11010 `
b11100 c
b101 B
b1001000010101001101 C
b10010010000000000000000000000000000000000000000 E
b111111111111111111011110100011100010100010111101 '
b111111111111111111011110100011100010100010111101 Z
1&
#300
0&
#305
b11101 ^
b100 B
b10010000101010011010 C
b100100100000000000000000000000000000000000000000 E
b11011 #
b11011 `
b11101 c
b111111111111111110010110101010110101100000101101 '
b111111111111111110010110101010110101100000101101 Z
1&
#310
0&
#315
b11110 ^
b11100 #
b11100 `
b11110 c
b11 B
b100100001010100110101 C
b1001000000000000000000000000000000000000000000 E
b111111111111111110110010101001110010011001100101 '
b111111111111111110110010101001110010011001100101 Z
1&
#320
0&
#325
b11111 ^
b10 B
b1001000010101001101010 C
b10010000000000000000000000000000000000000000000 E
b11101 #
b11101 `
b11111 c
1&
#330
0&
#335
b0 ^
b11110 #
b11110 `
b100000 c
b1 B
b10010000101010011010100 C
b100100000000000000000000000000000000000000000000 E
1&
#340
0&
#345
b1 ^
b0 B
b100100001010100110101001 C
b1000000000000000000000000000000000000000000000 E
b11111 #
b11111 `
b100001 c
1&
#350
0&
#355
1\
b10 ^
b10 =
b100000 #
b100000 `
b100010 c
0A
14
b100100001010100110101001 5
b100100001010100110101001 D
1&
#360
0&
#365
b11 =
04
1A
b11000 B
b0 C
b100100001010100110101001001000000000000000000000 E
b10 ?
08
b100100001010100110101001 9
1&
#370
0&
#375
b10111 B
b1 C
b1000010101001101010010010000000000000000000000 E
b11 ?
b10011000000000000000000000000 :
1&
#380
0&
#385
b0 =
b1 L
b10110 B
b10 C
b10000101010011010100100100000000000000000000000 E
1.
b10011100100001010100110101001 /
b10011100100001010100110101001 ;
b10011100100001010100110101001 F
1&
#390
0&
#395
b10 L
b10101 B
b100 C
b100001010100110101001001000000000000000000000000 E
b1 N
x)
0J
b10011100100001010100110101001 K
b0 ?
1&
#400
0&
#405
b0 T
b10100 B
b1001 C
b10101001101010010010000000000000000000000000 E
1*
10
0.
b0 >
b111111111111111111000000100010010101111010000001 7
b111111111111111111000000100010010101111010000001 @
b10 N
b1001110010000101010011 I
1&
#410
0&
#415
b10 T
b10011 B
b10010 C
b101010011010100100100000000000000000000000000 E
1)
1J
0M
b1001110010000101010011 %
b1001110010000101010011 2
b1001110010000101010011 H
1!
b0 W
1&
