envelope_detection/hdl/log_frac_calc.v
module log_frac_calc #(
    parameter DATA_WIDTH = 48,
    parameter FRAC_WIDTH = 16,
    parameter NORM_WIDTH = FRAC_WIDTH + 1
) (
    input clk,
    input reset,
    input in_valid,
    input out_ready,
    input [NORM_WIDTH-1:0] data_in,
    output reg out_valid,
    output in_ready,
    output reg [NORM_WIDTH-1:0] log_frac_out
);

    reg [FRAC_WIDTH-1:0] log2_constants [FRAC_WIDTH-1:0];
    reg [NORM_WIDTH-1:0] cordic_x_constants [FRAC_WIDTH-1:0];

    initial begin
        log2_constants[0] = 16'h8000;
        log2_constants[1] = 16'h95d3;
        log2_constants[2] = 16'h515a;
        log2_constants[3] = 16'h2c71;
        log2_constants[4] = 16'h166b;
        log2_constants[5] = 16'h0b6f;
        log2_constants[6] = 16'h05c0;
        log2_constants[7] = 16'h02e8;
        log2_constants[8] = 16'h0175;
        log2_constants[9] = 16'h00ba;
        log2_constants[10] = 16'h005d;
        log2_constants[11] = 16'h002f;
        log2_constants[12] = 16'h0018;
        log2_constants[13] = 16'h000c;
        log2_constants[14] = 16'h0006;
        log2_constants[15] = 16'h0003;
    end

    initial begin
        cordic_x_constants[0] = 17'h18000;
        cordic_x_constants[1] = 17'h1C000;
        cordic_x_constants[2] = 17'h1A000;
        cordic_x_constants[3] = 17'h19000;
        cordic_x_constants[4] = 17'h18800;
        cordic_x_constants[5] = 17'h18400;
        cordic_x_constants[6] = 17'h18200;
        cordic_x_constants[7] = 17'h18100;
        cordic_x_constants[8] = 17'h18080;
        cordic_x_constants[9] = 17'h18040;
        cordic_x_constants[10] = 17'h18020;
        cordic_x_constants[11] = 17'h18010;
        cordic_x_constants[12] = 17'h18008;
        cordic_x_constants[13] = 17'h18004;
        cordic_x_constants[14] = 17'h18002;
        cordic_x_constants[15] = 17'h18001;
    end

    reg [NORM_WIDTH-1:0] x_reg;
    reg [NORM_WIDTH-1:0] z_reg = 0;
    reg [$clog2(NORM_WIDTH):0] i = 1;

    reg [1:0] state, next_state;
    localparam IDLE = 0, CALC = 1, DONE = 2;

    always @(*) begin
        case(state)
            IDLE: next_state = (in_valid && in_ready) ? CALC : IDLE;
            CALC: next_state = (i == 16) ? DONE : CALC;
            DONE: next_state = (out_valid && out_ready) ? IDLE : DONE;
        endcase
    end

    always @(posedge clk ) begin
        if (reset) begin
            state <= IDLE;
            out_valid <= 0;
            log_frac_out <= 0;
            x_reg <= 0;
            z_reg <= 0;
            i <= 1;
        end else begin
            case(state)
                IDLE: begin
                    if (in_ready && in_valid) begin
                        x_reg <= data_in;
                        z_reg <= 0;
                        i <= 1; 
                        out_valid <= 1;
                    end
                end 

                CALC: begin
                    if (x_reg >= cordic_x_constants[i]) begin
                        x_reg <= x_reg - (x_reg >> i);
                        
                        z_reg <= z_reg + log2_constants[i];
                    end else begin
                        x_reg <= x_reg;
                        z_reg <= z_reg;
                    end

                    i <= i + 1;
                end 

                DONE: begin
                    log_frac_out <= z_reg;
                    out_valid <= 1'b1;
                end
            endcase

            state <= next_state;
        end
    end

    assign in_ready = (state == IDLE);

endmodule

ultrasound/verilog/logc/int_calc.v
module int_calc #(
    parameter DATA_WIDTH = 16,
    parameter FRAC_WIDTH = 16,
    parameter MIN_THRESHOLD = 1,
    parameter NORM_WIDTH = FRAC_WIDTH + 1,
    parameter SHIFT_WIDTH = $clog2(DATA_WIDTH)
) (
    input clk,
    input reset,
    input in_valid,
    input out_ready,
    input [DATA_WIDTH-1:0] data_in,
    output reg out_valid,
    output in_ready,
    output reg [SHIFT_WIDTH-1:0] int_part,
    output reg [NORM_WIDTH-1:0] data_out
);
    reg [DATA_WIDTH-1:0] sample_reg;
    reg [DATA_WIDTH-1:0] zp_reg;
    reg [DATA_WIDTH-1:0] shift_reg;
    reg [SHIFT_WIDTH-1:0] msb_index;
    integer i;

    reg found = 0;

    localparam IDLE = 0, CALC_ZP = 1, PROCESS = 2, CALC_SHIFT = 3, LOAD_DOUT = 4, SEND = 5;
    reg [2:0] state, next_state;

    always @(*) begin
        case(state)
            IDLE: next_state = (in_ready && in_valid) ? CALC_ZP : IDLE;
            CALC_ZP: next_state = PROCESS;
            PROCESS: next_state = CALC_SHIFT;
            CALC_SHIFT: next_state = LOAD_DOUT;
            LOAD_DOUT: next_state = SEND;
            SEND: next_state = (out_ready) ? IDLE : SEND;
        endcase
    end

    always @(posedge clk) begin
        if (reset) begin
            sample_reg <= 0;
            out_valid <= 0;
            state <= IDLE;
            found <= 1'b0;
        end else begin
            case(state)
                IDLE: begin
                    if (in_ready && in_valid) begin
                        sample_reg <= data_in;
                    end
                end

                CALC_ZP: begin
                    zp_reg <= (sample_reg == 0) ? MIN_THRESHOLD : sample_reg;
                end

                PROCESS: begin
                    for (i = 0; i <= DATA_WIDTH-1; i = i + 1) begin
                        if (zp_reg[i]) begin
                            if (~found) begin
                                msb_index <= i;
                                found <= 1'b1;
                            end
                        end
                    end
                end

                CALC_SHIFT: begin
                    shift_reg <= zp_reg >> (msb_index - (NORM_WIDTH - 1));
                end

                LOAD_DOUT: begin
                    int_part <= msb_index;

                    data_out <= {1'b1, shift_reg[15:0]};                    
                    out_valid <= 1'b1;
                end

                SEND: begin
                    found <= 1'b0;
                    out_valid <= 1'b0;
                end
            endcase

            state <= next_state;
        end
    end

    assign in_ready = (state == IDLE);

endmodule

ultrasound/libero/hdl/top_logc.v
module top_logc #(
    parameter DATA_WIDTH = 48,
    parameter FRAC_WIDTH = 16,
    parameter MIN_THRESHOLD = 1,
    parameter NORM_WIDTH = FRAC_WIDTH + 1,
    parameter SHIFT_WIDTH = $clog2(DATA_WIDTH)
) (
    input clk,
    input reset,
    input [DATA_WIDTH-1:0] data_in,
    input fifo_out_valid,
    output log_in_ready,
    output [SHIFT_WIDTH-1:0] comp_int,
    output [NORM_WIDTH-1:0] comp_frac
);

wire int_in_valid;
wire int_out_ready;
wire int_out_valid;
// wire int_in_ready;
wire [NORM_WIDTH-1:0] int_data_out;

wire frac_in_valid;
wire frac_out_ready;
wire frac_out_valid;
wire frac_in_ready;

assign int_in_valid = fifo_out_valid;
assign int_out_ready = frac_in_ready;
assign frac_in_valid = int_out_valid;
assign frac_out_ready = 1'b1;

int_calc #(
    .DATA_WIDTH(DATA_WIDTH),
    .FRAC_WIDTH(FRAC_WIDTH),
    .MIN_THRESHOLD(MIN_THRESHOLD),
    .NORM_WIDTH(NORM_WIDTH),
    .SHIFT_WIDTH(SHIFT_WIDTH)
) int_calc_0 (
    .clk(clk),
    .reset(reset),
    .in_valid(int_in_valid),
    .out_ready(int_out_ready),
    .data_in(data_in),
    .out_valid(int_out_valid),
    .in_ready(log_in_ready),
    .int_part(comp_int),
    .data_out(int_data_out)
);

log_frac_calc # (
    .DATA_WIDTH(DATA_WIDTH),
    .FRAC_WIDTH(FRAC_WIDTH),
    .NORM_WIDTH(NORM_WIDTH)
) log_frac_calc_0 (
    .clk(clk),
    .reset(reset),
    .in_valid(frac_in_valid),
    .out_ready(frac_out_ready),
    .data_in(int_data_out),
    .out_valid(frac_out_valid),
    .in_ready(frac_in_ready),
    .log_frac_out(comp_frac)
);

endmodule

envelope_detection/hdl/fifo.v
module fifo #(
    parameter DATA_WIDTH = 16
) (
    input clk,
    input reset,
    input [DATA_WIDTH-1:0] data_in,
    input wr_en,
    input rd_en,

    output wire [DATA_WIDTH-1:0] data_out,
    output wire [ADDR_WIDTH:0]   fifo_count,
    output wire out_valid
);

    localparam DEPTH = 30;
    localparam ADDR_WIDTH = $clog2(DEPTH);

    reg [DATA_WIDTH-1:0] fifo_mem [0:DEPTH-1];

    reg [ADDR_WIDTH:0] wr_ptr_ext;
    reg [ADDR_WIDTH:0] rd_ptr_ext;

    wire [ADDR_WIDTH-1:0] wr_ptr;
    wire [ADDR_WIDTH-1:0] rd_ptr;
    wire full;
    wire empty;

    assign wr_ptr = wr_ptr_ext[ADDR_WIDTH-1:0];
    assign rd_ptr = rd_ptr_ext[ADDR_WIDTH-1:0];

    assign data_out = fifo_mem[rd_ptr];

    assign empty = (wr_ptr_ext == rd_ptr_ext);

    assign full = ((wr_ptr_ext[ADDR_WIDTH] != rd_ptr_ext[ADDR_WIDTH]) && (wr_ptr == rd_ptr));

    assign out_valid = !empty;

    assign fifo_count = wr_ptr_ext - rd_ptr_ext;

    always @(posedge clk or posedge reset) begin
        if (reset) begin
            wr_ptr_ext <= 0;
            rd_ptr_ext <= 0;
        end else begin
            if (wr_en && !full) begin
                fifo_mem[wr_ptr] <= data_in;
                wr_ptr_ext <= wr_ptr_ext + 1;
            end

            if (rd_en && !empty) begin
                rd_ptr_ext <= rd_ptr_ext + 1;
            end
        end
    end

endmodule

ultrasound/tb/logc/tb_top_logc.v
`timescale 1ps/1ps

module tb_top_logc;
    reg [DATA_WIDTH-1:0] data_lut [0:2];
    reg [1:0] i = 0;

    parameter DEPTH = 30;

    localparam DATA_WIDTH = 48;
    localparam FRAC_WIDTH = 16;
    localparam MIN_THRESHOLD = 1;
    localparam NORM_WIDTH = FRAC_WIDTH + 1;
    localparam SHIFT_WIDTH = $clog2(DATA_WIDTH);

    localparam ADDR_WIDTH = $clog2(DEPTH);

    reg clk;
    reg reset;
    reg [DATA_WIDTH-1:0] data_in;
    wire [DATA_WIDTH-1:0] data_out;
    wire [ADDR_WIDTH:0] fifo_count;
    wire [ADDR_WIDTH-1:0] rd_ptr;
    wire [ADDR_WIDTH-1:0] wr_ptr;
    wire [SHIFT_WIDTH-1:0] comp_int;
    wire [NORM_WIDTH-1:0] comp_frac;
    wire pir;
    wire fifo_out_valid;

    fifo # (
        DATA_WIDTH,
    ) fifo_inst (
        .clk(clk),
        .reset(reset),
        .data_in(data_in),
        .rd_en(pir),
        .wr_en(1'b1),
        .data_out(data_out),
        .fifo_count(fifo_count),
        .out_valid(fifo_out_valid)
    );

    top_logc #(
        .DATA_WIDTH(DATA_WIDTH),
        .FRAC_WIDTH(FRAC_WIDTH),
        .MIN_THRESHOLD(MIN_THRESHOLD),
        .NORM_WIDTH(NORM_WIDTH),
        .SHIFT_WIDTH(SHIFT_WIDTH)
    ) top_logc_0 (
        .clk(clk),
        .reset(reset),
        .data_in(data_out),
        .log_in_ready(pir),
        .fifo_out_valid(fifo_out_valid),
        .comp_int(comp_int),
        .comp_frac(comp_frac)
    );

    initial begin
        data_lut[0] = 48'd120362;
        data_lut[1] = 48'd65536;
        data_lut[2] = 48'd1;
    end

    initial begin
        clk = 0;
        forever #5 clk = ~clk;
    end

    initial begin
        reset = 1;
        data_in = 0;
        #20;
        reset = 0;
        repeat (30) begin
            @(posedge clk);
            data_in = data_lut[i];
            i <= i + 1;
        end
        #1000;
        $finish;
    end

    initial begin
        $dumpfile("top_logc_tb.vcd");
        $dumpvars(0, tb_top_logc);
    end

endmodule

ultrasound/vcb/top_logc_tb.vcd
$date
	Sat Aug 23 17:28:09 2025
$end
$version
	Icarus Verilog
$end
$timescale
	1ps
$end
$scope module tb_top_logc $end
$var wire 1 ! pir $end
$var wire 1 " fifo_out_valid $end
$var wire 6 # fifo_count [5:0] $end
$var wire 48 $ data_out [47:0] $end
$var wire 6 % comp_int [5:0] $end
$var wire 17 & comp_frac [16:0] $end
$var reg 1 ' clk $end
$var reg 48 ( data_in [47:0] $end
$var reg 2 ) i [1:0] $end
$var reg 1 * reset $end
$scope module fifo_inst $end
$var wire 1 ' clk $end
$var wire 48 + data_in [47:0] $end
$var wire 48 , data_out [47:0] $end
$var wire 1 - full $end
$var wire 1 * reset $end
$var wire 1 . wr_en $end
$var wire 5 / wr_ptr [4:0] $end
$var wire 5 0 rd_ptr [4:0] $end
$var wire 1 ! rd_en $end
$var wire 1 " out_valid $end
$var wire 6 1 fifo_count [5:0] $end
$var wire 1 2 empty $end
$var reg 6 3 rd_ptr_ext [5:0] $end
$var reg 6 4 wr_ptr_ext [5:0] $end
$upscope $end
$scope module top_logc_0 $end
$var wire 1 ' clk $end
$var wire 48 5 data_in [47:0] $end
$var wire 1 " fifo_out_valid $end
$var wire 1 6 frac_in_valid $end
$var wire 1 7 frac_out_ready $end
$var wire 1 8 int_in_valid $end
$var wire 1 9 int_out_ready $end
$var wire 1 * reset $end
$var wire 1 ! log_in_ready $end
$var wire 1 : int_out_valid $end
$var wire 17 ; int_data_out [16:0] $end
$var wire 1 < frac_out_valid $end
$var wire 1 = frac_in_ready $end
$var wire 6 > comp_int [5:0] $end
$var wire 17 ? comp_frac [16:0] $end
$scope module int_calc_0 $end
$var wire 1 ' clk $end
$var wire 48 @ data_in [47:0] $end
$var wire 1 8 in_valid $end
$var wire 1 9 out_ready $end
$var wire 1 * reset $end
$var wire 1 ! in_ready $end
$var reg 17 A data_out [16:0] $end
$var reg 1 B found $end
$var reg 6 C int_part [5:0] $end
$var reg 6 D msb_index [5:0] $end
$var reg 3 E next_state [2:0] $end
$var reg 1 : out_valid $end
$var reg 48 F sample_reg [47:0] $end
$var reg 48 G shift_reg [47:0] $end
$var reg 3 H state [2:0] $end
$var reg 48 I zp_reg [47:0] $end
$var integer 32 J i [31:0] $end
$upscope $end
$scope module log_frac_calc_0 $end
$var wire 1 ' clk $end
$var wire 17 K data_in [16:0] $end
$var wire 1 6 in_valid $end
$var wire 1 7 out_ready $end
$var wire 1 * reset $end
$var wire 1 = in_ready $end
$var reg 6 L i [5:0] $end
$var reg 17 M log_frac_out [16:0] $end
$var reg 2 N next_state [1:0] $end
$var reg 1 < out_valid $end
$var reg 2 O state [1:0] $end
$var reg 17 P x_reg [16:0] $end
$var reg 17 Q z_reg [16:0] $end
$upscope $end
$upscope $end
$upscope $end
$enddefinitions $end
#0
$dumpvars
b0 Q
bx P
bx O
bx N
bx M
b1 L
bx K
bx J
bx I
bx H
bx G
bx F
bx E
bx D
bx C
0B
bx A
bx @
bx ?
bx >
x=
x<
bx ;
x:
x9
08
17
x6
bx 5
b0 4
b0 3
12
b0 1
b0 0
b0 /
1.
0-
bx ,
b0 +
1*
b0 )
b0 (
0'
bx &
bx %
bx $
b0 #
0"
x!
$end
#5
b0 E
b0 N
1!
b0 H
06
0:
b0 F
b0 P
b0 &
b0 ?
b0 M
0<
19
1=
b0 O
1'
#10
0'
#15
1'
#20
0'
0*
#25
b1 /
b1 E
18
1"
02
b1 #
b1 1
b1 4
b11101011000101010 $
b11101011000101010 ,
b11101011000101010 5
b11101011000101010 @
bx F
b1 )
b11101011000101010 (
b11101011000101010 +
1'
#30
0'
#35
b10000000000000000 $
b10000000000000000 ,
b10000000000000000 5
b10000000000000000 @
b1 0
b10 /
b10 E
b1 3
b1 #
b1 1
b10 4
b10 )
0!
b1 H
b11101011000101010 F
b10000000000000000 (
b10000000000000000 +
1'
#40
0'
#45
b11 /
b11 E
b10 #
b10 1
b11 4
b10 H
b11101011000101010 I
b11 )
b1 (
b1 +
1'
#50
0'
#55
b100 /
b100 E
b11 #
b11 1
b100 4
b0 )
b11 H
1B
b10000 D
bx (
bx +
b110000 J
1'
#60
0'
#65
b101 /
b101 E
b100 #
b100 1
b101 4
b100 H
b11101011000101010 G
b1 )
b11101011000101010 (
b11101011000101010 +
1'
#70
0'
#75
b110 /
b0 E
b1 N
b101 #
b101 1
b110 4
b10 )
b101 H
16
1:
b11101011000101010 ;
b11101011000101010 A
b11101011000101010 K
b10000 %
b10000 >
b10000 C
b10000000000000000 (
b10000000000000000 +
1'
#80
0'
#85
b111 /
b1 E
b110 #
b110 1
b111 4
1!
b0 H
06
0:
0B
09
0=
b1 O
1<
b11101011000101010 P
b11 )
b1 (
b1 +
1'
#90
0'
#95
b1 $
b1 ,
b1 5
b1 @
b10 0
b1000 /
b10 E
b10 3
b110 #
b110 1
b1000 4
b0 )
b10 L
b1001010111010011 Q
b1110101100010101 P
0!
b1 H
b10000000000000000 F
bx (
bx +
1'
#100
0'
#105
b1001 /
b11 E
b111 #
b111 1
b1001 4
b10 H
b10000000000000000 I
b11 L
b1 )
b11101011000101010 (
b11101011000101010 +
1'
#110
0'
#115
b1010 /
b100 E
b1000 #
b1000 1
b1010 4
b10 )
b100 L
b11 H
1B
b10000000000000000 (
b10000000000000000 +
b110000 J
1'
#120
0'
#125
b1011 /
b101 E
b1001 #
b1001 1
b1011 4
b100 H
b10000000000000000 G
b101 L
b11 )
b1 (
b1 +
1'
#130
0'
#135
b1100 /
b1010 #
b1010 1
b1100 4
b0 )
b110 L
b101 H
16
1:
b10000000000000000 ;
b10000000000000000 A
b10000000000000000 K
bx (
bx +
1'
#140
0'
#145
b1101 /
b1011 #
b1011 1
b1101 4
06
0:
0B
b111 L
b1 )
b11101011000101010 (
b11101011000101010 +
1'
#150
0'
#155
b1110 /
b1100 #
b1100 1
b1110 4
b10 )
b1000 L
b10000000000000000 (
b10000000000000000 +
1'
#160
0'
#165
b1111 /
b1101 #
b1101 1
b1111 4
b1001 L
b11 )
b1 (
b1 +
1'
#170
0'
#175
b10000 /
b1110 #
b1110 1
b10000 4
b0 )
b1010 L
bx (
bx +
1'
#180
0'
#185
b10001 /
b1111 #
b1111 1
b10001 4
b1011 L
b1 )
b11101011000101010 (
b11101011000101010 +
1'
#190
0'
#195
b10010 /
b10000 #
b10000 1
b10010 4
b10 )
b1100 L
b10000000000000000 (
b10000000000000000 +
1'
#200
0'
#205
b10011 /
b10001 #
b10001 1
b10011 4
b1101 L
b11 )
b1 (
b1 +
1'
#210
0'
#215
b10100 /
b10010 #
b10010 1
b10100 4
b0 )
b1110 L
bx (
bx +
1'
#220
0'
#225
b10101 /
b10011 #
b10011 1
b10101 4
b1111 L
b1 )
b11101011000101010 (
b11101011000101010 +
1'
#230
0'
#235
b10110 /
b10 N
b10100 #
b10100 1
b10110 4
b10 )
b10000 L
b10000000000000000 (
b10000000000000000 +
1'
#240
0'
#245
b10111 /
b0 N
b10101 #
b10101 1
b10111 4
b10 O
b10001 L
b11 )
b1 (
b1 +
1'
#250
0'
#255
b11000 /
b0 E
b10110 #
b10110 1
b11000 4
b0 )
19
1=
b0 O
b1001010111010011 &
b1001010111010011 ?
b1001010111010011 M
bx (
bx +
1'
#260
0'
#265
b11001 /
b1 E
b10111 #
b10111 1
b11001 4
1!
b0 H
b1 )
b11101011000101010 (
b11101011000101010 +
1'
#270
0'
#275
bx $
bx ,
bx 5
bx @
b11 0
b11010 /
b10 E
b11 3
b10111 #
b10111 1
b11010 4
b10 )
0!
b1 H
b1 F
b10000000000000000 (
b10000000000000000 +
1'
#280
0'
#285
b11011 /
b11 E
b11000 #
b11000 1
b11011 4
b10 H
b1 I
b11 )
b1 (
b1 +
1'
#290
0'
#295
b11100 /
b100 E
b11001 #
b11001 1
b11100 4
b0 )
b11 H
1B
b0 D
bx (
bx +
b110000 J
1'
#300
0'
#305
b11101 /
b101 E
b11010 #
b11010 1
b11101 4
b100 H
b0 G
b1 )
b11101011000101010 (
b11101011000101010 +
1'
#310
0'
#315
b11110 /
b0 E
b1 N
b11011 #
b11011 1
b11110 4
b10 )
b101 H
16
1:
b0 %
b0 >
b0 C
b10000000000000000 (
b10000000000000000 +
1'
#320
0'
#325
b11111 /
b1 E
b11100 #
b11100 1
b11111 4
1!
b0 H
06
0:
0B
09
0=
b1 O
b1 L
b0 Q
b10000000000000000 P
1'
#330
0'
#335
b11101011000101010 $
b11101011000101010 ,
b11101011000101010 5
b11101011000101010 @
b100 0
b0 /
b10 E
b100 3
b11100 #
b11100 1
b100000 4
b10 L
0!
b1 H
bx F
1'
#340
0'
#345
b1 /
b11 E
b11101 #
b11101 1
b100001 4
b10 H
bx I
b11 L
1'
#350
0'
#355
b10 /
b100 E
b11110 #
b11110 1
b100010 4
b100 L
b11 H
b110000 J
1'
#360
0'
#365
b11 /
b101 E
b11111 #
b11111 1
b100011 4
b100 H
b101 L
1'
#370
0'
#375
1-
b100 /
b100000 #
b100000 1
b100100 4
b110 L
b101 H
16
1:
1'
#380
0'
#385
06
0:
b111 L
1'
#390
0'
#395
b1000 L
1'
#400
0'
#405
b1001 L
1'
#410
0'
#415
b1010 L
1'
#420
0'
#425
b1011 L
1'
#430
0'
#435
b1100 L
1'
#440
0'
#445
b1101 L
1'
#450
0'
#455
b1110 L
1'
#460
0'
#465
b1111 L
1'
#470
0'
#475
b10 N
b10000 L
1'
#480
0'
#485
b0 N
b10 O
b10001 L
1'
#490
0'
#495
b0 E
19
1=
b0 O
b0 &
b0 ?
b0 M
1'
#500
0'
#505
b1 E
1!
b0 H
1'
#510
0'
#515
0-
b10000000000000000 $
b10000000000000000 ,
b10000000000000000 5
b10000000000000000 @
b101 0
b10 E
b11111 #
b11111 1
b101 3
0!
b1 H
b11101011000101010 F
1'
#520
0'
#525
1-
b101 /
b11 E
b100000 #
b100000 1
b100101 4
b10 H
b11101011000101010 I
1'
#530
0'
#535
b100 E
b11 H
1B
b10000 D
b110000 J
1'
#540
0'
#545
b101 E
b100 H
b11101011000101010 G
1'
#550
0'
#555
b0 E
b1 N
b101 H
16
1:
b11101011000101010 ;
b11101011000101010 A
b11101011000101010 K
b10000 %
b10000 >
b10000 C
1'
#560
0'
#565
b1 E
1!
b0 H
06
0:
0B
09
0=
b1 O
b1 L
b11101011000101010 P
1'
#570
0'
#575
0-
b1 $
b1 ,
b1 5
b1 @
b110 0
b10 E
b11111 #
b11111 1
b110 3
b10 L
b1001010111010011 Q
b1110101100010101 P
0!
b1 H
b10000000000000000 F
1'
#580
0'
#585
1-
b110 /
b11 E
b100000 #
b100000 1
b100110 4
b10 H
b10000000000000000 I
b11 L
1'
#590
0'
#595
b100 E
b100 L
b11 H
1B
b110000 J
1'
#600
0'
#605
b101 E
b100 H
b10000000000000000 G
b101 L
1'
#610
0'
#615
b110 L
b101 H
16
1:
b10000000000000000 ;
b10000000000000000 A
b10000000000000000 K
1'
#620
0'
#625
06
0:
0B
b111 L
1'
#630
0'
#635
b1000 L
1'
#640
0'
#645
b1001 L
1'
#650
0'
#655
b1010 L
1'
#660
0'
#665
b1011 L
1'
#670
0'
#675
b1100 L
1'
#680
0'
#685
b1101 L
1'
#690
0'
#695
b1110 L
1'
#700
0'
#705
b1111 L
1'
#710
0'
#715
b10 N
b10000 L
1'
#720
0'
#725
b0 N
b10 O
b10001 L
1'
#730
0'
#735
b0 E
19
1=
b0 O
b1001010111010011 &
b1001010111010011 ?
b1001010111010011 M
1'
#740
0'
#745
b1 E
1!
b0 H
1'
#750
0'
#755
0-
bx $
bx ,
bx 5
bx @
b111 0
b10 E
b11111 #
b11111 1
b111 3
0!
b1 H
b1 F
1'
#760
0'
#765
1-
b111 /
b11 E
b100000 #
b100000 1
b100111 4
b10 H
b1 I
1'
#770
0'
#775
b100 E
b11 H
1B
b0 D
b110000 J
1'
#780
0'
#785
b101 E
b100 H
b0 G
1'
#790
0'
#795
b0 E
b1 N
b101 H
16
1:
b0 %
b0 >
b0 C
1'
#800
0'
#805
b1 E
1!
b0 H
06
0:
0B
09
0=
b1 O
b1 L
b0 Q
b10000000000000000 P
1'
#810
0'
#815
0-
b11101011000101010 $
b11101011000101010 ,
b11101011000101010 5
b11101011000101010 @
b1000 0
b10 E
b11111 #
b11111 1
b1000 3
b10 L
0!
b1 H
bx F
1'
#820
0'
#825
1-
b1000 /
b11 E
b100000 #
b100000 1
b101000 4
b10 H
bx I
b11 L
1'
#830
0'
#835
b100 E
b100 L
b11 H
b110000 J
1'
#840
0'
#845
b101 E
b100 H
b101 L
1'
#850
0'
#855
b110 L
b101 H
16
1:
1'
#860
0'
#865
06
0:
b111 L
1'
#870
0'
#875
b1000 L
1'
#880
0'
#885
b1001 L
1'
#890
0'
#895
b1010 L
1'
#900
0'
#905
b1011 L
1'
#910
0'
#915
b1100 L
1'
#920
0'
#925
b1101 L
1'
#930
0'
#935
b1110 L
1'
#940
0'
#945
b1111 L
1'
#950
0'
#955
b10 N
b10000 L
1'
#960
0'
#965
b0 N
b10 O
b10001 L
1'
#970
0'
#975
b0 E
19
1=
b0 O
b0 &
b0 ?
b0 M
1'
#980
0'
#985
b1 E
1!
b0 H
1'
#990
0'
#995
0-
b10000000000000000 $
b10000000000000000 ,
b10000000000000000 5
b10000000000000000 @
b1001 0
b10 E
b11111 #
b11111 1
b1001 3
0!
b1 H
b11101011000101010 F
1'
#1000
0'
#1005
1-
b1001 /
b11 E
b100000 #
b100000 1
b101001 4
b10 H
b11101011000101010 I
1'
#1010
0'
#1015
b100 E
b11 H
1B
b10000 D
b110000 J
1'
#1020
0'
#1025
b101 E
b100 H
b11101011000101010 G
1'
#1030
0'
#1035
b0 E
b1 N
b101 H
16
1:
b11101011000101010 ;
b11101011000101010 A
b11101011000101010 K
b10000 %
b10000 >
b10000 C
1'
#1040
0'
#1045
b1 E
1!
b0 H
06
0:
0B
09
0=
b1 O
b1 L
b11101011000101010 P
1'
#1050
0'
#1055
0-
b1 $
b1 ,
b1 5
b1 @
b1010 0
b10 E
b11111 #
b11111 1
b1010 3
b10 L
b1001010111010011 Q
b1110101100010101 P
0!
b1 H
b10000000000000000 F
1'
#1060
0'
#1065
1-
b1010 /
b11 E
b100000 #
b100000 1
b101010 4
b10 H
b10000000000000000 I
b11 L
1'
#1070
0'
#1075
b100 E
b100 L
b11 H
1B
b110000 J
1'
#1080
0'
#1085
b101 E
b100 H
b10000000000000000 G
b101 L
1'
#1090
0'
#1095
b110 L
b101 H
16
1:
b10000000000000000 ;
b10000000000000000 A
b10000000000000000 K
1'
#1100
0'
#1105
06
0:
0B
b111 L
1'
#1110
0'
#1115
b1000 L
1'
#1120
0'
#1125
b1001 L
1'
#1130
0'
#1135
b1010 L
1'
#1140
0'
#1145
b1011 L
1'
#1150
0'
#1155
b1100 L
1'
#1160
0'
#1165
b1101 L
1'
#1170
0'
#1175
b1110 L
1'
#1180
0'
#1185
b1111 L
1'
#1190
0'
#1195
b10 N
b10000 L
1'
#1200
0'
#1205
b0 N
b10 O
b10001 L
1'
#1210
0'
#1215
b0 E
19
1=
b0 O
b1001010111010011 &
b1001010111010011 ?
b1001010111010011 M
1'
#1220
0'
#1225
b1 E
1!
b0 H
1'
#1230
0'
#1235
0-
bx $
bx ,
bx 5
bx @
b1011 0
b10 E
b11111 #
b11111 1
b1011 3
0!
b1 H
b1 F
1'
#1240
0'
#1245
1-
b1011 /
b11 E
b100000 #
b100000 1
b101011 4
b10 H
b1 I
1'
#1250
0'
#1255
b100 E
b11 H
1B
b0 D
b110000 J
1'
#1260
0'
#1265
b101 E
b100 H
b0 G
1'
#1270
0'
#1275
b0 E
b1 N
b101 H
16
1:
b0 %
b0 >
b0 C
1'
#1280
0'
#1285
b1 E
1!
b0 H
06
0:
0B
09
0=
b1 O
b1 L
b0 Q
b10000000000000000 P
1'
#1290
0'
#1295
0-
b11101011000101010 $
b11101011000101010 ,
b11101011000101010 5
b11101011000101010 @
b1100 0
b10 E
b11111 #
b11111 1
b1100 3
b10 L
0!
b1 H
bx F
1'
#1300
0'
#1305
1-
b1100 /
b11 E
b100000 #
b100000 1
b101100 4
b10 H
bx I
b11 L
1'
#1310
0'
#1315
b100 E
b100 L
b11 H
b110000 J
1'
