envelope_detection/hdl/log_frac_calc.v
module log_frac_calc #(
    parameter DATA_WIDTH = 48,
    parameter FRAC_WIDTH = 16,
    parameter NORM_WIDTH = FRAC_WIDTH + 1
) (
    input clk,
    input reset,
    input in_valid,
    input out_ready,
    input [NORM_WIDTH-1:0] data_in,
    output reg out_valid,
    output in_ready,
    output reg [NORM_WIDTH-1:0] log_frac_out
);

    reg [FRAC_WIDTH-1:0] log2_constants [FRAC_WIDTH-1:0];
    reg [NORM_WIDTH-1:0] cordic_x_constants [FRAC_WIDTH-1:0];

    initial begin
        log2_constants[0] = 16'h8000;
        log2_constants[1] = 16'h95d3;
        log2_constants[2] = 16'h515a;
        log2_constants[3] = 16'h2c71;
        log2_constants[4] = 16'h166b;
        log2_constants[5] = 16'h0b6f;
        log2_constants[6] = 16'h05c0;
        log2_constants[7] = 16'h02e8;
        log2_constants[8] = 16'h0175;
        log2_constants[9] = 16'h00ba;
        log2_constants[10] = 16'h005d;
        log2_constants[11] = 16'h002f;
        log2_constants[12] = 16'h0018;
        log2_constants[13] = 16'h000c;
        log2_constants[14] = 16'h0006;
        log2_constants[15] = 16'h0003;
    end

    initial begin
        cordic_x_constants[0] = 17'h18000;
        cordic_x_constants[1] = 17'h1C000;
        cordic_x_constants[2] = 17'h1A000;
        cordic_x_constants[3] = 17'h19000;
        cordic_x_constants[4] = 17'h18800;
        cordic_x_constants[5] = 17'h18400;
        cordic_x_constants[6] = 17'h18200;
        cordic_x_constants[7] = 17'h18100;
        cordic_x_constants[8] = 17'h18080;
        cordic_x_constants[9] = 17'h18040;
        cordic_x_constants[10] = 17'h18020;
        cordic_x_constants[11] = 17'h18010;
        cordic_x_constants[12] = 17'h18008;
        cordic_x_constants[13] = 17'h18004;
        cordic_x_constants[14] = 17'h18002;
        cordic_x_constants[15] = 17'h18001;
    end

    reg [NORM_WIDTH-1:0] x_reg;
    reg [NORM_WIDTH-1:0] z_reg = 0;
    reg [$clog2(NORM_WIDTH):0] i = 1;

    reg [1:0] state, next_state;
    localparam IDLE = 0, CALC = 1, DONE = 2;

    always @(*) begin
        case(state)
            IDLE: next_state = (in_valid && in_ready) ? CALC : IDLE;
            CALC: next_state = (i == 16) ? DONE : CALC;
            DONE: next_state = (out_valid && out_ready) ? IDLE : DONE;
        endcase
    end

    always @(posedge clk ) begin
        if (reset) begin
            state <= IDLE;
            out_valid <= 0;
            log_frac_out <= 0;
            x_reg <= 0;
            z_reg <= 0;
            i <= 1;
        end else begin
            case(state)
                IDLE: begin
                    if (in_ready && in_valid) begin
                        x_reg <= data_in;
                        z_reg <= 0;
                        i <= 1; 
                        out_valid <= 1;
                    end
                end 

                CALC: begin
                    if (x_reg >= cordic_x_constants[i]) begin
                        x_reg <= x_reg - (x_reg >> i);
                        
                        z_reg <= z_reg + log2_constants[i];
                    end else begin
                        x_reg <= x_reg;
                        z_reg <= z_reg;
                    end

                    i <= i + 1;
                end 

                DONE: begin
                    log_frac_out <= z_reg;
                    out_valid <= 1'b1;
                end
            endcase

            state <= next_state;
        end
    end

    assign in_ready = (state == IDLE);

endmodule

ultrasound/verilog/logc/int_calc.v
module int_calc #(
    parameter DATA_WIDTH = 16,
    parameter FRAC_WIDTH = 16,
    parameter MIN_THRESHOLD = 1,
    parameter NORM_WIDTH = FRAC_WIDTH + 1,
    parameter SHIFT_WIDTH = $clog2(DATA_WIDTH)
) (
    input clk,
    input reset,
    input in_valid,
    input out_ready,
    input [DATA_WIDTH-1:0] data_in,
    output reg out_valid,
    output in_ready,
    output reg [SHIFT_WIDTH-1:0] int_part,
    output reg [NORM_WIDTH-1:0] data_out
);
    reg [DATA_WIDTH-1:0] sample_reg;
    reg [DATA_WIDTH-1:0] zp_reg;
    reg [DATA_WIDTH-1:0] shift_reg;
    reg [SHIFT_WIDTH-1:0] msb_index;
    integer i;

    reg found = 0;

    localparam IDLE = 0, CALC_ZP = 1, PROCESS = 2, CALC_SHIFT = 3, LOAD_DOUT = 4, SEND = 5;
    reg [2:0] state, next_state;

    always @(*) begin
        case(state)
            IDLE: next_state = (in_ready && in_valid) ? CALC_ZP : IDLE;
            CALC_ZP: next_state = PROCESS;
            PROCESS: next_state = CALC_SHIFT;
            CALC_SHIFT: next_state = LOAD_DOUT;
            LOAD_DOUT: next_state = SEND;
            SEND: next_state = (out_ready) ? IDLE : SEND;
        endcase
    end

    always @(posedge clk) begin
        if (reset) begin
            sample_reg <= 0;
            out_valid <= 0;
            state <= IDLE;
            found <= 1'b0;
        end else begin
            case(state)
                IDLE: begin
                    if (in_ready && in_valid) begin
                        sample_reg <= data_in;
                    end
                end

                CALC_ZP: begin
                    zp_reg <= (sample_reg == 0) ? MIN_THRESHOLD : sample_reg;
                end

                PROCESS: begin
                    for (i = 0; i <= DATA_WIDTH-1; i = i + 1) begin
                        if (zp_reg[i]) begin
                            if (~found) begin
                                msb_index <= i;
                                found <= 1'b1;
                            end
                        end
                    end
                end

                CALC_SHIFT: begin
                    shift_reg <= zp_reg >> (msb_index - (NORM_WIDTH - 1));
                end

                LOAD_DOUT: begin
                    int_part <= msb_index;

                    data_out <= {1'b1, shift_reg[15:0]};                    
                    out_valid <= 1'b1;
                end

                SEND: begin
                    found <= 1'b0;
                    out_valid <= 1'b0;
                end
            endcase

            state <= next_state;
        end
    end

    assign in_ready = (state == IDLE);

endmodule

ultrasound/libero/hdl/top_logc.v
module top_logc #(
    parameter DATA_WIDTH = 48,
    parameter FRAC_WIDTH = 16,
    parameter MIN_THRESHOLD = 1,
    parameter NORM_WIDTH = FRAC_WIDTH + 1,
    parameter SHIFT_WIDTH = $clog2(DATA_WIDTH)
) (
    input clk,
    input reset,
    input [DATA_WIDTH-1:0] data_in,
    input fifo_out_valid,
    output log_in_ready,
    output [SHIFT_WIDTH-1:0] comp_int,
    output [NORM_WIDTH-1:0] comp_frac
);

wire int_in_valid;
wire int_out_ready;
wire int_out_valid;
// wire int_in_ready;
wire [NORM_WIDTH-1:0] int_data_out;

wire frac_in_valid;
wire frac_out_ready;
wire frac_out_valid;
wire frac_in_ready;

assign int_in_valid = fifo_out_valid;
assign int_out_ready = frac_in_ready;
assign frac_in_valid = int_out_valid;
assign frac_out_ready = 1'b1;

int_calc #(
    .DATA_WIDTH(DATA_WIDTH),
    .FRAC_WIDTH(FRAC_WIDTH),
    .MIN_THRESHOLD(MIN_THRESHOLD),
    .NORM_WIDTH(NORM_WIDTH),
    .SHIFT_WIDTH(SHIFT_WIDTH)
) int_calc_0 (
    .clk(clk),
    .reset(reset),
    .in_valid(int_in_valid),
    .out_ready(int_out_ready),
    .data_in(data_in),
    .out_valid(int_out_valid),
    .in_ready(log_in_ready),
    .int_part(comp_int),
    .data_out(int_data_out)
);

log_frac_calc # (
    .DATA_WIDTH(DATA_WIDTH),
    .FRAC_WIDTH(FRAC_WIDTH),
    .NORM_WIDTH(NORM_WIDTH)
) log_frac_calc_0 (
    .clk(clk),
    .reset(reset),
    .in_valid(frac_in_valid),
    .out_ready(frac_out_ready),
    .data_in(int_data_out),
    .out_valid(frac_out_valid),
    .in_ready(frac_in_ready),
    .log_frac_out(comp_frac)
);

endmodule

envelope_detection/hdl/fifo.v
module fifo #(
    parameter DATA_WIDTH = 16
) (
    input clk,
    input reset,
    input [DATA_WIDTH-1:0] data_in,
    input wr_en,
    input rd_en,

    output wire [DATA_WIDTH-1:0] data_out,
    output wire [ADDR_WIDTH:0]   fifo_count,
    output wire out_valid
);

    localparam DEPTH = 30;
    localparam ADDR_WIDTH = $clog2(DEPTH);

    reg [DATA_WIDTH-1:0] fifo_mem [0:DEPTH-1];

    reg [ADDR_WIDTH:0] wr_ptr_ext;
    reg [ADDR_WIDTH:0] rd_ptr_ext;

    wire [ADDR_WIDTH-1:0] wr_ptr;
    wire [ADDR_WIDTH-1:0] rd_ptr;
    wire full;
    wire empty;

    assign wr_ptr = wr_ptr_ext[ADDR_WIDTH-1:0];
    assign rd_ptr = rd_ptr_ext[ADDR_WIDTH-1:0];

    assign data_out = fifo_mem[rd_ptr];

    assign empty = (wr_ptr_ext == rd_ptr_ext);

    assign full = ((wr_ptr_ext[ADDR_WIDTH] != rd_ptr_ext[ADDR_WIDTH]) && (wr_ptr == rd_ptr));

    assign out_valid = !empty;

    assign fifo_count = wr_ptr_ext - rd_ptr_ext;

    always @(posedge clk or posedge reset) begin
        if (reset) begin
            wr_ptr_ext <= 0;
            rd_ptr_ext <= 0;
        end else begin
            if (wr_en && !full) begin
                fifo_mem[wr_ptr] <= data_in;
                wr_ptr_ext <= wr_ptr_ext + 1;
            end

            if (rd_en && !empty) begin
                rd_ptr_ext <= rd_ptr_ext + 1;
            end
        end
    end

endmodule

ultrasound/tb/logc/tb_top_logc.v
`timescale 1ps/1ps

module tb_top_logc;
    // reg [DATA_WIDTH-1:0] data_lut [0:2];
    // reg [1:0] i = 0;

    parameter DEPTH = 30;

    localparam DATA_WIDTH = 48;
    localparam FRAC_WIDTH = 16;
    localparam MIN_THRESHOLD = 1;
    localparam NORM_WIDTH = FRAC_WIDTH + 1;
    localparam SHIFT_WIDTH = $clog2(DATA_WIDTH);

    localparam ADDR_WIDTH = $clog2(DEPTH);

    reg clk;
    reg reset;
    reg [DATA_WIDTH-1:0] data_in;
    wire [DATA_WIDTH-1:0] data_out;
    wire [ADDR_WIDTH:0] fifo_count;
    wire [ADDR_WIDTH-1:0] rd_ptr;
    wire [ADDR_WIDTH-1:0] wr_ptr;
    wire [SHIFT_WIDTH-1:0] comp_int;
    wire [NORM_WIDTH-1:0] comp_frac;
    wire pir;
    wire fifo_out_valid;

    fifo # (
        DATA_WIDTH,
    ) fifo_inst (
        .clk(clk),
        .reset(reset),
        .data_in(data_in),
        .rd_en(pir),
        .wr_en(1'b1),
        .data_out(data_out),
        .fifo_count(fifo_count),
        .out_valid(fifo_out_valid)
    );

    top_logc #(
        .DATA_WIDTH(DATA_WIDTH),
        .FRAC_WIDTH(FRAC_WIDTH),
        .MIN_THRESHOLD(MIN_THRESHOLD),
        .NORM_WIDTH(NORM_WIDTH),
        .SHIFT_WIDTH(SHIFT_WIDTH)
    ) top_logc_0 (
        .clk(clk),
        .reset(reset),
        .data_in(data_out),
        .log_in_ready(pir),
        .fifo_out_valid(fifo_out_valid),
        .comp_int(comp_int),
        .comp_frac(comp_frac)
    );

    // initial begin
    //     data_lut[0] = 48'd120362;
    //     data_lut[1] = 48'd65536;
    //     data_lut[2] = 48'd1;
    // end

    initial begin
        clk = 0;
        forever #5 clk = ~clk;
    end

    initial begin
        reset = 1;
        data_in = 0;
        #20;
        reset = 0;
        repeat (30) begin
            @(posedge clk);
            data_in = $random;
        end
        #1000;
        $finish;
    end

    initial begin
        $dumpfile("top_logc_tb.vcd");
        $dumpvars(0, tb_top_logc);
    end

endmodule

ultrasound/vcb/top_logc_tb.vcd
$date
	Sun Aug 24 00:35:35 2025
$end
$version
	Icarus Verilog
$end
$timescale
	1ps
$end
$scope module tb_top_logc $end
$var wire 1 ! pir $end
$var wire 1 " fifo_out_valid $end
$var wire 6 # fifo_count [5:0] $end
$var wire 48 $ data_out [47:0] $end
$var wire 6 % comp_int [5:0] $end
$var wire 17 & comp_frac [16:0] $end
$var reg 1 ' clk $end
$var reg 48 ( data_in [47:0] $end
$var reg 1 ) reset $end
$scope module fifo_inst $end
$var wire 1 ' clk $end
$var wire 48 * data_in [47:0] $end
$var wire 48 + data_out [47:0] $end
$var wire 1 , full $end
$var wire 1 ) reset $end
$var wire 1 - wr_en $end
$var wire 5 . wr_ptr [4:0] $end
$var wire 5 / rd_ptr [4:0] $end
$var wire 1 ! rd_en $end
$var wire 1 " out_valid $end
$var wire 6 0 fifo_count [5:0] $end
$var wire 1 1 empty $end
$var reg 6 2 rd_ptr_ext [5:0] $end
$var reg 6 3 wr_ptr_ext [5:0] $end
$upscope $end
$scope module top_logc_0 $end
$var wire 1 ' clk $end
$var wire 48 4 data_in [47:0] $end
$var wire 1 " fifo_out_valid $end
$var wire 1 5 frac_in_valid $end
$var wire 1 6 frac_out_ready $end
$var wire 1 7 int_in_valid $end
$var wire 1 8 int_out_ready $end
$var wire 1 ) reset $end
$var wire 1 ! log_in_ready $end
$var wire 1 9 int_out_valid $end
$var wire 17 : int_data_out [16:0] $end
$var wire 1 ; frac_out_valid $end
$var wire 1 < frac_in_ready $end
$var wire 6 = comp_int [5:0] $end
$var wire 17 > comp_frac [16:0] $end
$scope module int_calc_0 $end
$var wire 1 ' clk $end
$var wire 48 ? data_in [47:0] $end
$var wire 1 7 in_valid $end
$var wire 1 8 out_ready $end
$var wire 1 ) reset $end
$var wire 1 ! in_ready $end
$var reg 17 @ data_out [16:0] $end
$var reg 1 A found $end
$var reg 6 B int_part [5:0] $end
$var reg 6 C msb_index [5:0] $end
$var reg 3 D next_state [2:0] $end
$var reg 1 9 out_valid $end
$var reg 48 E sample_reg [47:0] $end
$var reg 48 F shift_reg [47:0] $end
$var reg 3 G state [2:0] $end
$var reg 48 H zp_reg [47:0] $end
$var integer 32 I i [31:0] $end
$upscope $end
$scope module log_frac_calc_0 $end
$var wire 1 ' clk $end
$var wire 17 J data_in [16:0] $end
$var wire 1 5 in_valid $end
$var wire 1 6 out_ready $end
$var wire 1 ) reset $end
$var wire 1 < in_ready $end
$var reg 6 K i [5:0] $end
$var reg 17 L log_frac_out [16:0] $end
$var reg 2 M next_state [1:0] $end
$var reg 1 ; out_valid $end
$var reg 2 N state [1:0] $end
$var reg 17 O x_reg [16:0] $end
$var reg 17 P z_reg [16:0] $end
$upscope $end
$upscope $end
$upscope $end
$enddefinitions $end
#0
$dumpvars
b0 P
bx O
bx N
bx M
bx L
b1 K
bx J
bx I
bx H
bx G
bx F
bx E
bx D
bx C
bx B
0A
bx @
bx ?
bx >
bx =
x<
x;
bx :
x9
x8
07
16
x5
bx 4
b0 3
b0 2
11
b0 0
b0 /
b0 .
1-
0,
bx +
b0 *
1)
b0 (
0'
bx &
bx %
bx $
b0 #
0"
x!
$end
#5
b0 D
b0 M
1!
b0 G
05
09
b0 E
b0 O
b0 &
b0 >
b0 L
0;
18
1<
b0 N
1'
#10
0'
#15
1'
#20
0'
0)
#25
b1 .
b1 D
17
1"
01
b1 #
b1 0
b1 3
b10010000101010011010100100100 $
b10010000101010011010100100100 +
b10010000101010011010100100100 4
b10010000101010011010100100100 ?
b10010000101010011010100100100 (
b10010000101010011010100100100 *
1'
#30
0'
#35
b111111111111111111000000100010010101111010000001 $
b111111111111111111000000100010010101111010000001 +
b111111111111111111000000100010010101111010000001 4
b111111111111111111000000100010010101111010000001 ?
b1 /
b10 .
b10 D
b1 2
b1 #
b1 0
b10 3
0!
b1 G
b10010000101010011010100100100 E
b111111111111111111000000100010010101111010000001 (
b111111111111111111000000100010010101111010000001 *
1'
#40
0'
#45
b11 .
b11 D
b10 #
b10 0
b11 3
b10 G
b10010000101010011010100100100 H
b111111111111111110000100100001001101011000001001 (
b111111111111111110000100100001001101011000001001 *
1'
#50
0'
#55
b100 .
b100 D
b11 #
b11 0
b100 3
b11 G
1A
b11100 C
b111111111111111110110001111100000101011001100011 (
b111111111111111110110001111100000101011001100011 *
b110000 I
1'
#60
0'
#65
b101 .
b101 D
b100 #
b100 0
b101 3
b100 G
b10010000101010011 F
b110101110010111101100001101 (
b110101110010111101100001101 *
1'
#70
0'
#75
b110 .
b0 D
b1 M
b101 #
b101 0
b110 3
b101 G
15
19
b10010000101010011 :
b10010000101010011 @
b10010000101010011 J
b11100 %
b11100 =
b11100 B
b1000110110111111001100110001101 (
b1000110110111111001100110001101 *
1'
#80
0'
#85
b111 .
b1 D
b110 #
b110 0
b111 3
1!
b0 G
05
09
0A
08
0<
b1 N
1;
b10010000101010011 O
b111111111111111110110010110000101000010001100101 (
b111111111111111110110010110000101000010001100101 *
1'
#90
0'
#95
b111111111111111110000100100001001101011000001001 $
b111111111111111110000100100001001101011000001001 +
b111111111111111110000100100001001101011000001001 4
b111111111111111110000100100001001101011000001001 ?
b10 /
b1000 .
b10 D
b10 2
b110 #
b110 0
b1000 3
b10 K
0!
b1 G
b111111111111111111000000100010010101111010000001 E
b111111111111111110001001001101110101001000010010 (
b111111111111111110001001001101110101001000010010 *
1'
#100
0'
#105
b1001 .
b11 D
b111 #
b111 0
b1001 3
b10 G
b111111111111111111000000100010010101111010000001 H
b11 K
b111100111110001100000001 (
b111100111110001100000001 *
1'
#110
0'
#115
b1010 .
b100 D
b1000 #
b1000 0
b1010 3
b100 K
b11 G
1A
b101111 C
b110110101111100110100001101 (
b110110101111100110100001101 *
b110000 I
1'
#120
0'
#125
b1011 .
b101 D
b1001 #
b1001 0
b1011 3
b100 G
b11111111111111111 F
b101 K
b111011001000111111000101110110 (
b111011001000111111000101110110 *
1'
#130
0'
#135
b1100 .
b1010 #
b1010 0
b1100 3
b110 K
b101 G
15
19
b11111111111111111 :
b11111111111111111 @
b11111111111111111 J
b101111 %
b101111 =
b101111 B
b11110100011011100110100111101 (
b11110100011011100110100111101 *
1'
#140
0'
#145
b1101 .
b1011 #
b1011 0
b1101 3
05
09
0A
b111 K
b1110110110101000101011111101101 (
b1110110110101000101011111101101 *
1'
#150
0'
#155
b1110 .
b1100 #
b1100 0
b1110 3
b1000 K
b1000110001011011111011110001100 (
b1000110001011011111011110001100 *
1'
#160
0'
#165
b1111 .
b1101 #
b1101 0
b1111 3
b1001 K
b1111100111111011110100111111001 (
b1111100111111011110100111111001 *
1'
#170
0'
#175
b10000 .
b1110 #
b1110 0
b10000 3
b1010 K
b111111111111111111100011001101110010010011000110 (
b111111111111111111100011001101110010010011000110 *
1'
#180
0'
#185
b10001 .
b1111 #
b1111 0
b10001 3
b1011 K
b111111111111111111100010111101111000010011000101 (
b111111111111111111100010111101111000010011000101 *
1'
#190
0'
#195
b10010 .
b10000 #
b10000 0
b10010 3
b1100 K
b111111111111111111010101000100111101001010101010 (
b111111111111111111010101000100111101001010101010 *
1'
#200
0'
#205
b10011 .
b10001 #
b10001 0
b10011 3
b1101 K
b1110010101011111111011111100101 (
b1110010101011111111011111100101 *
1'
#210
0'
#215
b10100 .
b10010 #
b10010 0
b10100 3
b1110 K
b111111111111111110111011110100100111001001110111 (
b111111111111111110111011110100100111001001110111 *
1'
#220
0'
#225
b10101 .
b10011 #
b10011 0
b10101 3
b1111 K
b111111111111111110001001001100101101011000010010 (
b111111111111111110001001001100101101011000010010 *
1'
#230
0'
#235
b10110 .
b10 M
b10100 #
b10100 0
b10110 3
b10000 K
b1000111111011001101101110001111 (
b1000111111011001101101110001111 *
1'
#240
0'
#245
b10111 .
b0 M
b10101 #
b10101 0
b10111 3
b10 N
b10001 K
b1111001001100000110100111110010 (
b1111001001100000110100111110010 *
1'
#250
0'
#255
b11000 .
b0 D
b10110 #
b10110 0
b11000 3
18
1<
b0 N
b111111111111111111100111011101101001011011001110 (
b111111111111111111100111011101101001011011001110 *
1'
#260
0'
#265
b11001 .
b1 D
b10111 #
b10111 0
b11001 3
1!
b0 G
b111111111111111111110100000000000111101011101000 (
b111111111111111111110100000000000111101011101000 *
1'
#270
0'
#275
b111111111111111110110001111100000101011001100011 $
b111111111111111110110001111100000101011001100011 +
b111111111111111110110001111100000101011001100011 4
b111111111111111110110001111100000101011001100011 ?
b11 /
b11010 .
b10 D
b11 2
b10111 #
b10111 0
b11010 3
0!
b1 G
b111111111111111110000100100001001101011000001001 E
b111111111111111111100010110010100100111011000101 (
b111111111111111111100010110010100100111011000101 *
1'
#280
0'
#285
b11011 .
b11 D
b11000 #
b11000 0
b11011 3
b10 G
b111111111111111110000100100001001101011000001001 H
b101110010110000100100101011100 (
b101110010110000100100101011100 *
1'
#290
0'
#295
b11100 .
b100 D
b11001 #
b11001 0
b11100 3
b11 G
1A
b101111 C
b111111111111111111011110100011100010100010111101 (
b111111111111111111011110100011100010100010111101 *
b110000 I
1'
#300
0'
#305
b11101 .
b101 D
b11010 #
b11010 0
b11101 3
b100 G
b111111111111111110010110101010110101100000101101 (
b111111111111111110010110101010110101100000101101 *
1'
#310
0'
#315
b11110 .
b0 D
b1 M
b11011 #
b11011 0
b11110 3
b101 G
15
19
b111111111111111110110010101001110010011001100101 (
b111111111111111110110010101001110010011001100101 *
1'
#320
0'
#325
b11111 .
b1 D
b11100 #
b11100 0
b11111 3
1!
b0 G
05
09
0A
08
0<
b1 N
b1 K
b11111111111111111 O
1'
#330
0'
#335
b110101110010111101100001101 $
b110101110010111101100001101 +
b110101110010111101100001101 4
b110101110010111101100001101 ?
b100 /
b0 .
b10 D
b100 2
b11100 #
b11100 0
b100000 3
b10 K
b1001010111010011 P
b10000000000000000 O
0!
b1 G
b111111111111111110110001111100000101011001100011 E
1'
#340
0'
#345
b1 .
b11 D
b11101 #
b11101 0
b100001 3
b10 G
b111111111111111110110001111100000101011001100011 H
b11 K
1'
#350
0'
#355
b10 .
b100 D
b11110 #
b11110 0
b100010 3
b100 K
b11 G
1A
b101111 C
b110000 I
1'
#360
0'
#365
b11 .
b101 D
b11111 #
b11111 0
b100011 3
b100 G
b101 K
1'
#370
0'
#375
1,
b100 .
b100000 #
b100000 0
b100100 3
b110 K
b101 G
15
19
1'
#380
0'
#385
05
09
0A
b111 K
1'
#390
0'
#395
b1000 K
1'
#400
0'
#405
b1001 K
1'
#410
0'
#415
b1010 K
1'
#420
0'
#425
b1011 K
1'
#430
0'
#435
b1100 K
1'
#440
0'
#445
b1101 K
1'
#450
0'
#455
b1110 K
1'
#460
0'
#465
b1111 K
1'
#470
0'
#475
b10 M
b10000 K
1'
#480
0'
#485
b0 M
b10 N
b10001 K
1'
#490
0'
#495
b0 D
18
1<
b0 N
b1001010111010011 &
b1001010111010011 >
b1001010111010011 L
1'
#500
0'
#505
b1 D
1!
b0 G
1'
#510
0'
#515
0,
b1000110110111111001100110001101 $
b1000110110111111001100110001101 +
b1000110110111111001100110001101 4
b1000110110111111001100110001101 ?
b101 /
b10 D
b11111 #
b11111 0
b101 2
0!
b1 G
b110101110010111101100001101 E
1'
#520
0'
#525
1,
b101 .
b11 D
b100000 #
b100000 0
b100101 3
b10 G
b110101110010111101100001101 H
1'
#530
0'
#535
b100 D
b11 G
1A
b11010 C
b110000 I
1'
#540
0'
#545
b101 D
b100 G
b11010111001011110 F
1'
#550
0'
#555
b0 D
b1 M
b101 G
15
19
b11010111001011110 :
b11010111001011110 @
b11010111001011110 J
b11010 %
b11010 =
b11010 B
1'
#560
0'
#565
b1 D
1!
b0 G
05
09
0A
08
0<
b1 N
b1 K
b0 P
b11010111001011110 O
1'
#570
0'
#575
0,
b111111111111111110110010110000101000010001100101 $
b111111111111111110110010110000101000010001100101 +
b111111111111111110110010110000101000010001100101 4
b111111111111111110110010110000101000010001100101 ?
b110 /
b10 D
b11111 #
b11111 0
b110 2
b10 K
0!
b1 G
b1000110110111111001100110001101 E
1'
#580
0'
#585
1,
b110 .
b11 D
b100000 #
b100000 0
b100110 3
b10 G
b1000110110111111001100110001101 H
b11 K
b101000101011010 P
b10100001011000111 O
1'
#590
0'
#595
b100 D
b100 K
b11 G
1A
b11110 C
b110000 I
1'
#600
0'
#605
b101 D
b100 G
b10001101101111110 F
b101 K
1'
#610
0'
#615
b110 K
b101 G
15
19
b10001101101111110 :
b10001101101111110 @
b10001101101111110 J
b11110 %
b11110 =
b11110 B
1'
#620
0'
#625
05
09
0A
b111 K
1'
#630
0'
#635
b1000 K
1'
#640
0'
#645
b1001 K
1'
#650
0'
#655
b1010 K
1'
#660
0'
#665
b1011 K
1'
#670
0'
#675
b1100 K
1'
#680
0'
#685
b1101 K
1'
#690
0'
#695
b1110 K
1'
#700
0'
#705
b1111 K
1'
#710
0'
#715
b10 M
b10000 K
1'
#720
0'
#725
b0 M
b10 N
b10001 K
1'
#730
0'
#735
b0 D
18
1<
b0 N
b101000101011010 &
b101000101011010 >
b101000101011010 L
1'
#740
0'
#745
b1 D
1!
b0 G
1'
#750
0'
#755
0,
b111111111111111110001001001101110101001000010010 $
b111111111111111110001001001101110101001000010010 +
b111111111111111110001001001101110101001000010010 4
b111111111111111110001001001101110101001000010010 ?
b111 /
b10 D
b11111 #
b11111 0
b111 2
0!
b1 G
b111111111111111110110010110000101000010001100101 E
1'
#760
0'
#765
1,
b111 .
b11 D
b100000 #
b100000 0
b100111 3
b10 G
b111111111111111110110010110000101000010001100101 H
1'
#770
0'
#775
b100 D
b11 G
1A
b101111 C
b110000 I
1'
#780
0'
#785
b101 D
b100 G
b11111111111111111 F
1'
#790
0'
#795
b0 D
b1 M
b101 G
15
19
b11111111111111111 :
b11111111111111111 @
b11111111111111111 J
b101111 %
b101111 =
b101111 B
1'
#800
0'
#805
b1 D
1!
b0 G
05
09
0A
08
0<
b1 N
b1 K
b0 P
b11111111111111111 O
1'
#810
0'
#815
0,
b111100111110001100000001 $
b111100111110001100000001 +
b111100111110001100000001 4
b111100111110001100000001 ?
b1000 /
b10 D
b11111 #
b11111 0
b1000 2
b10 K
b1001010111010011 P
b10000000000000000 O
0!
b1 G
b111111111111111110001001001101110101001000010010 E
1'
#820
0'
#825
1,
b1000 .
b11 D
b100000 #
b100000 0
b101000 3
b10 G
b111111111111111110001001001101110101001000010010 H
b11 K
1'
#830
0'
#835
b100 D
b100 K
b11 G
1A
b101111 C
b110000 I
1'
#840
0'
#845
b101 D
b100 G
b101 K
1'
#850
0'
#855
b110 K
b101 G
15
19
1'
#860
0'
#865
05
09
0A
b111 K
1'
#870
0'
#875
b1000 K
1'
#880
0'
#885
b1001 K
1'
#890
0'
#895
b1010 K
1'
#900
0'
#905
b1011 K
1'
#910
0'
#915
b1100 K
1'
#920
0'
#925
b1101 K
1'
#930
0'
#935
b1110 K
1'
#940
0'
#945
b1111 K
1'
#950
0'
#955
b10 M
b10000 K
1'
#960
0'
#965
b0 M
b10 N
b10001 K
1'
#970
0'
#975
b0 D
18
1<
b0 N
b1001010111010011 &
b1001010111010011 >
b1001010111010011 L
1'
#980
0'
#985
b1 D
1!
b0 G
1'
#990
0'
#995
0,
b110110101111100110100001101 $
b110110101111100110100001101 +
b110110101111100110100001101 4
b110110101111100110100001101 ?
b1001 /
b10 D
b11111 #
b11111 0
b1001 2
0!
b1 G
b111100111110001100000001 E
1'
#1000
0'
#1005
1,
b1001 .
b11 D
b100000 #
b100000 0
b101001 3
b10 G
b111100111110001100000001 H
1'
#1010
0'
#1015
b100 D
b11 G
1A
b10111 C
b110000 I
1'
#1020
0'
#1025
b101 D
b100 G
b11110011111000110 F
1'
#1030
0'
#1035
b0 D
b1 M
b101 G
15
19
b11110011111000110 :
b11110011111000110 @
b11110011111000110 J
b10111 %
b10111 =
b10111 B
1'
#1040
0'
#1045
b1 D
1!
b0 G
05
09
0A
08
0<
b1 N
b1 K
b0 P
b11110011111000110 O
1'
#1050
0'
#1055
0,
b111011001000111111000101110110 $
b111011001000111111000101110110 +
b111011001000111111000101110110 4
b111011001000111111000101110110 ?
b1010 /
b10 D
b11111 #
b11111 0
b1010 2
b10 K
b1001010111010011 P
b1111001111100011 O
0!
b1 G
b110110101111100110100001101 E
1'
#1060
0'
#1065
1,
b1010 .
b11 D
b100000 #
b100000 0
b101010 3
b10 G
b110110101111100110100001101 H
b11 K
1'
#1070
0'
#1075
b100 D
b100 K
b11 G
1A
b11010 C
b110000 I
1'
#1080
0'
#1085
b101 D
b100 G
b11011010111110011 F
b101 K
1'
#1090
0'
#1095
b110 K
b101 G
15
19
b11011010111110011 :
b11011010111110011 @
b11011010111110011 J
b11010 %
b11010 =
b11010 B
1'
#1100
0'
#1105
05
09
0A
b111 K
1'
#1110
0'
#1115
b1000 K
1'
#1120
0'
#1125
b1001 K
1'
#1130
0'
#1135
b1010 K
1'
#1140
0'
#1145
b1011 K
1'
#1150
0'
#1155
b1100 K
1'
#1160
0'
#1165
b1101 K
1'
#1170
0'
#1175
b1110 K
1'
#1180
0'
#1185
b1111 K
1'
#1190
0'
#1195
b10 M
b10000 K
1'
#1200
0'
#1205
b0 M
b10 N
b10001 K
1'
#1210
0'
#1215
b0 D
18
1<
b0 N
1'
#1220
0'
#1225
b1 D
1!
b0 G
1'
#1230
0'
#1235
0,
b11110100011011100110100111101 $
b11110100011011100110100111101 +
b11110100011011100110100111101 4
b11110100011011100110100111101 ?
b1011 /
b10 D
b11111 #
b11111 0
b1011 2
0!
b1 G
b111011001000111111000101110110 E
1'
#1240
0'
#1245
1,
b1011 .
b11 D
b100000 #
b100000 0
b101011 3
b10 G
b111011001000111111000101110110 H
1'
#1250
0'
#1255
b100 D
b11 G
1A
b11101 C
b110000 I
1'
#1260
0'
#1265
b101 D
b100 G
b11101100100011111 F
1'
#1270
0'
#1275
b0 D
b1 M
b101 G
15
19
b11101100100011111 :
b11101100100011111 @
b11101100100011111 J
b11101 %
b11101 =
b11101 B
1'
#1280
0'
#1285
b1 D
1!
b0 G
05
09
0A
08
0<
b1 N
b1 K
b0 P
b11101100100011111 O
1'
#1290
0'
#1295
0,
b1110110110101000101011111101101 $
b1110110110101000101011111101101 +
b1110110110101000101011111101101 4
b1110110110101000101011111101101 ?
b1100 /
b10 D
b11111 #
b11111 0
b1100 2
b10 K
b1001010111010011 P
b1110110010010000 O
0!
b1 G
b11110100011011100110100111101 E
1'
#1300
0'
#1305
1,
b1100 .
b11 D
b100000 #
b100000 0
b101100 3
b10 G
b11110100011011100110100111101 H
b11 K
1'
#1310
0'
#1315
b100 D
b100 K
b11 G
1A
b11100 C
b110000 I
1'
