ultrasound/verilog/logc/log_frac_calc.v
module log_frac_calc #(
    parameter DATA_WIDTH = 48,
    parameter FRAC_WIDTH = 16,
    parameter NORM_WIDTH = FRAC_WIDTH + 1
) (
    input clk,
    input reset,
    input in_valid,
    input out_ready,
    input [NORM_WIDTH-1:0] data_in,      
    output reg out_valid,
    output in_ready,
    output reg [NORM_WIDTH-1:0] log_frac_out
);

    assign in_ready = (state == IDLE);

    localparam [NORM_WIDTH-1:0] ONE = {1'b1, {FRAC_WIDTH{1'b0}}};

    reg [NORM_WIDTH-1:0] x, y;
    reg [4:0] iter;
    reg [4:0] cycle_count;

    localparam IDLE    = 0,
               LOAD    = 1,
               ITERATE = 2,
               DONE    = 3;
    reg [1:0] state, next_state;

    reg [NORM_WIDTH-1:0] log_p_table [1:FRAC_WIDTH];
    initial begin
        log_p_table[1]  = 17'h095C0; log_p_table[2]  = 17'h05269;
        log_p_table[3]  = 17'h02B80; log_p_table[4]  = 17'h01663;
        log_p_table[5]  = 17'h00B5D; log_p_table[6]  = 17'h005B9;
        log_p_table[7]  = 17'h002E0; log_p_table[8]  = 17'h00171;
        log_p_table[9]  = 17'h000B9; log_p_table[10] = 17'h0005C;
        log_p_table[11] = 17'h0002E; log_p_table[12] = 17'h00017;
        log_p_table[13] = 17'h0000B; log_p_table[14] = 17'h00006;
        log_p_table[15] = 17'h00003; log_p_table[16] = 17'h00001;
    end
    
    reg [NORM_WIDTH-1:0] log_m_table [1:FRAC_WIDTH];
    initial begin
        log_m_table[1]  = 17'h10000; log_m_table[2]  = 17'h06A0A;
        log_m_table[3]  = 17'h03144; log_m_table[4]  = 17'h0174F;
        log_m_table[5]  = 17'h00B89; log_m_table[6]  = 17'h005C1;
        log_m_table[7]  = 17'h002E2; log_m_table[8]  = 17'h00171;
        log_m_table[9]  = 17'h000B9; log_m_table[10] = 17'h0005C;
        log_m_table[11] = 17'h0002E; log_m_table[12] = 17'h00017;
        log_m_table[13] = 17'h0000B; log_m_table[14] = 17'h00006;
        log_m_table[15] = 17'h00003; log_m_table[16] = 17'h00001;
    end

    localparam TOTAL_CYCLES = FRAC_WIDTH + 1;

    always @(*) begin
        case(state)
            IDLE:    next_state = (in_valid) ? LOAD : IDLE;
            LOAD:    next_state = ITERATE;
            ITERATE: next_state = (cycle_count == TOTAL_CYCLES) ? DONE : ITERATE;
            DONE:    next_state = (out_ready) ? IDLE : DONE;
            default: next_state = IDLE;
        endcase
    end

    always @(posedge clk) begin
        if (reset) begin
            state <= IDLE;
            out_valid <= 1'b0;
            iter <= 0;
            cycle_count <= 0;
            x <= 0;
            y <= 0;
            log_frac_out <= 0;
        end else begin
            state <= next_state;

            case(state)
                IDLE: begin
                    out_valid <= 1'b0;
                end

                LOAD: begin
                    x <= data_in;
                    y <= 0;
                    iter <= 1;
                    cycle_count <= 1;
                    out_valid <= 1'b0;
                end

                ITERATE: begin
                    if (cycle_count <= TOTAL_CYCLES) begin
                        if (x >= ONE) begin
                            x <= x - (x >>> iter);
                            y <= y + log_m_table[iter];
                        end else begin
                            x <= x + (x >>> iter);
                            y <= y - log_p_table[iter];
                        end
                        
                        cycle_count <= cycle_count + 1;
                        if (iter == 4 && cycle_count == 4) begin
                            iter <= 4; 
                        end else begin
                            iter <= iter + 1;
                        end
                    end
                end

                DONE: begin
                    log_frac_out <= y;
                    out_valid <= 1'b1;
                end
            endcase
        end
    end

endmodule

ultrasound/verilog/logc/int_calc.v
module int_calc #(
    parameter DATA_WIDTH = 16,
    parameter FRAC_WIDTH = 16,
    parameter MIN_THRESHOLD = 1,
    parameter NORM_WIDTH = FRAC_WIDTH + 1,
    parameter SHIFT_WIDTH = $clog2(DATA_WIDTH)
) (
    input clk,
    input reset,
    input in_valid,
    input out_ready,
    input [DATA_WIDTH-1:0] data_in,
    output reg out_valid,
    output in_ready,
    output reg [SHIFT_WIDTH-1:0] int_part,
    output reg [NORM_WIDTH-1:0] data_out
);
    reg [DATA_WIDTH-1:0] sample_reg;
    reg [DATA_WIDTH-1:0] zp_reg;
    reg [DATA_WIDTH-1:0] shift_reg;
    reg [SHIFT_WIDTH-1:0] msb_index;
    integer i;

    reg found = 0;

    localparam IDLE = 0, CALC_ZP = 1, PROCESS = 2, CALC_SHIFT = 3, LOAD_DOUT = 4, SEND = 5;
    reg [2:0] state, next_state;

    always @(*) begin
        case(state)
            IDLE: next_state = (in_ready && in_valid) ? CALC_ZP : IDLE;
            CALC_ZP: next_state = PROCESS;
            PROCESS: next_state = CALC_SHIFT;
            CALC_SHIFT: next_state = LOAD_DOUT;
            LOAD_DOUT: next_state = SEND;
            SEND: next_state = (out_ready) ? IDLE : SEND;
        endcase
    end

    always @(posedge clk) begin
        if (reset) begin
            sample_reg <= 0;
            out_valid <= 0;
            state <= IDLE;
            found <= 1'b0;
        end else begin
            case(state)
                IDLE: begin
                    if (in_ready && in_valid) begin
                        sample_reg <= data_in;
                    end
                end

                CALC_ZP: begin
                    zp_reg <= (sample_reg == 0) ? MIN_THRESHOLD : sample_reg;
                end

                PROCESS: begin
                    for (i = 0; i <= DATA_WIDTH-1; i = i + 1) begin
                        if (zp_reg[i]) begin
                            if (~found) begin
                                msb_index <= i;
                                found <= 1'b1;
                            end
                        end
                    end
                end

                CALC_SHIFT: begin
                    shift_reg <= zp_reg >> (msb_index - (NORM_WIDTH - 1));
                end

                LOAD_DOUT: begin
                    int_part <= msb_index;

                    data_out <= {1'b1, shift_reg[15:0]};                    
                    out_valid <= 1'b1;
                end

                SEND: begin
                    found <= 1'b0;
                    out_valid <= 1'b0;
                end
            endcase

            state <= next_state;
        end
    end

    assign in_ready = (state == IDLE);

endmodule

ultrasound/libero/hdl/top_logc.v
module top_logc #(
    parameter DATA_WIDTH = 48,
    parameter FRAC_WIDTH = 16,
    parameter MIN_THRESHOLD = 1,
    parameter NORM_WIDTH = FRAC_WIDTH + 1,
    parameter SHIFT_WIDTH = $clog2(DATA_WIDTH)
) (
    input clk,
    input reset,
    input [DATA_WIDTH-1:0] data_in,
    input fifo_out_valid,
    output log_in_ready,
    output [SHIFT_WIDTH-1:0] comp_int,
    output [NORM_WIDTH-1:0] comp_frac
);

wire int_in_valid;
wire int_out_ready;
wire int_out_valid;
// wire int_in_ready;
wire [NORM_WIDTH-1:0] int_data_out;

wire frac_in_valid;
wire frac_out_ready;
wire frac_out_valid;
wire frac_in_ready;

assign int_in_valid = fifo_out_valid;
assign int_out_ready = frac_in_ready;
assign frac_in_valid = int_out_valid;
assign frac_out_ready = 1'b1;

int_calc #(
    .DATA_WIDTH(DATA_WIDTH),
    .FRAC_WIDTH(FRAC_WIDTH),
    .MIN_THRESHOLD(MIN_THRESHOLD),
    .NORM_WIDTH(NORM_WIDTH),
    .SHIFT_WIDTH(SHIFT_WIDTH)
) int_calc_0 (
    .clk(clk),
    .reset(reset),
    .in_valid(int_in_valid),
    .out_ready(int_out_ready),
    .data_in(data_in),
    .out_valid(int_out_valid),
    .in_ready(log_in_ready),
    .int_part(comp_int),
    .data_out(int_data_out)
);

log_frac_calc # (
    .DATA_WIDTH(DATA_WIDTH),
    .FRAC_WIDTH(FRAC_WIDTH),
    .NORM_WIDTH(NORM_WIDTH)
) log_frac_calc_0 (
    .clk(clk),
    .reset(reset),
    .in_valid(frac_in_valid),
    .out_ready(frac_out_ready),
    .data_in(int_data_out),
    .out_valid(frac_out_valid),
    .in_ready(frac_in_ready),
    .log_frac_out(comp_frac)
);

endmodule

envelope_detection/hdl/fifo.v
module fifo #(
    parameter DATA_WIDTH = 16
) (
    input clk,
    input reset,
    input [DATA_WIDTH-1:0] data_in,
    input wr_en,
    input rd_en,

    output wire [DATA_WIDTH-1:0] data_out,
    output wire [ADDR_WIDTH:0]   fifo_count,
    output wire out_valid
);

    localparam DEPTH = 30;
    localparam ADDR_WIDTH = $clog2(DEPTH);

    reg [DATA_WIDTH-1:0] fifo_mem [0:DEPTH-1];

    reg [ADDR_WIDTH:0] wr_ptr_ext;
    reg [ADDR_WIDTH:0] rd_ptr_ext;

    wire [ADDR_WIDTH-1:0] wr_ptr;
    wire [ADDR_WIDTH-1:0] rd_ptr;
    wire full;
    wire empty;

    assign wr_ptr = wr_ptr_ext[ADDR_WIDTH-1:0];
    assign rd_ptr = rd_ptr_ext[ADDR_WIDTH-1:0];

    assign data_out = fifo_mem[rd_ptr];

    assign empty = (wr_ptr_ext == rd_ptr_ext);

    assign full = ((wr_ptr_ext[ADDR_WIDTH] != rd_ptr_ext[ADDR_WIDTH]) && (wr_ptr == rd_ptr));

    assign out_valid = !empty;

    assign fifo_count = wr_ptr_ext - rd_ptr_ext;

    always @(posedge clk or posedge reset) begin
        if (reset) begin
            wr_ptr_ext <= 0;
            rd_ptr_ext <= 0;
        end else begin
            if (wr_en && !full) begin
                fifo_mem[wr_ptr] <= data_in;
                wr_ptr_ext <= wr_ptr_ext + 1;
            end

            if (rd_en && !empty) begin
                rd_ptr_ext <= rd_ptr_ext + 1;
            end
        end
    end

endmodule

ultrasound/tb/logc/tb_top_logc.v
`timescale 1ps/1ps

module tb_top_logc;
    // reg [DATA_WIDTH-1:0] data_lut [0:2];
    // reg [1:0] i = 0;

    parameter DEPTH = 30;

    localparam DATA_WIDTH = 48;
    localparam FRAC_WIDTH = 16;
    localparam MIN_THRESHOLD = 1;
    localparam NORM_WIDTH = FRAC_WIDTH + 1;
    localparam SHIFT_WIDTH = $clog2(DATA_WIDTH);

    localparam ADDR_WIDTH = $clog2(DEPTH);

    reg clk;
    reg reset;
    reg [DATA_WIDTH-1:0] data_in;
    wire [DATA_WIDTH-1:0] data_out;
    wire [ADDR_WIDTH:0] fifo_count;
    wire [ADDR_WIDTH-1:0] rd_ptr;
    wire [ADDR_WIDTH-1:0] wr_ptr;
    wire [SHIFT_WIDTH-1:0] comp_int;
    wire [NORM_WIDTH-1:0] comp_frac;
    wire pir;
    wire fifo_out_valid;

    fifo # (
        DATA_WIDTH,
    ) fifo_inst (
        .clk(clk),
        .reset(reset),
        .data_in(data_in),
        .rd_en(pir),
        .wr_en(1'b1),
        .data_out(data_out),
        .fifo_count(fifo_count),
        .out_valid(fifo_out_valid)
    );

    top_logc #(
        .DATA_WIDTH(DATA_WIDTH),
        .FRAC_WIDTH(FRAC_WIDTH),
        .MIN_THRESHOLD(MIN_THRESHOLD),
        .NORM_WIDTH(NORM_WIDTH),
        .SHIFT_WIDTH(SHIFT_WIDTH)
    ) top_logc_0 (
        .clk(clk),
        .reset(reset),
        .data_in(data_out),
        .log_in_ready(pir),
        .fifo_out_valid(fifo_out_valid),
        .comp_int(comp_int),
        .comp_frac(comp_frac)
    );

    // initial begin
    //     data_lut[0] = 48'd120362;
    //     data_lut[1] = 48'd65536;
    //     data_lut[2] = 48'd1;
    // end

    initial begin
        clk = 0;
        forever #5 clk = ~clk;
    end

    initial begin
        reset = 1;
        data_in = 0;
        #20;
        reset = 0;
        data_in = 48'd987654321;
        #1000;
        $finish;
    end

    initial begin
        $dumpfile("top_logc_tb.vcd");
        $dumpvars(0, tb_top_logc);
    end

endmodule

ultrasound/vcb/top_logc_tb.vcd
$date
	Tue Sep  2 23:57:28 2025
$end
$version
	Icarus Verilog
$end
$timescale
	1ps
$end
$scope module tb_top_logc $end
$var wire 1 ! pir $end
$var wire 1 " fifo_out_valid $end
$var wire 6 # fifo_count [5:0] $end
$var wire 48 $ data_out [47:0] $end
$var wire 6 % comp_int [5:0] $end
$var wire 17 & comp_frac [16:0] $end
$var reg 1 ' clk $end
$var reg 48 ( data_in [47:0] $end
$var reg 1 ) reset $end
$scope module fifo_inst $end
$var wire 1 ' clk $end
$var wire 48 * data_in [47:0] $end
$var wire 48 + data_out [47:0] $end
$var wire 1 , full $end
$var wire 1 ) reset $end
$var wire 1 - wr_en $end
$var wire 5 . wr_ptr [4:0] $end
$var wire 5 / rd_ptr [4:0] $end
$var wire 1 ! rd_en $end
$var wire 1 " out_valid $end
$var wire 6 0 fifo_count [5:0] $end
$var wire 1 1 empty $end
$var reg 6 2 rd_ptr_ext [5:0] $end
$var reg 6 3 wr_ptr_ext [5:0] $end
$upscope $end
$scope module top_logc_0 $end
$var wire 1 ' clk $end
$var wire 48 4 data_in [47:0] $end
$var wire 1 " fifo_out_valid $end
$var wire 1 5 frac_in_valid $end
$var wire 1 6 frac_out_ready $end
$var wire 1 7 int_in_valid $end
$var wire 1 8 int_out_ready $end
$var wire 1 ) reset $end
$var wire 1 ! log_in_ready $end
$var wire 1 9 int_out_valid $end
$var wire 17 : int_data_out [16:0] $end
$var wire 1 ; frac_out_valid $end
$var wire 1 < frac_in_ready $end
$var wire 6 = comp_int [5:0] $end
$var wire 17 > comp_frac [16:0] $end
$scope module int_calc_0 $end
$var wire 1 ' clk $end
$var wire 48 ? data_in [47:0] $end
$var wire 1 7 in_valid $end
$var wire 1 8 out_ready $end
$var wire 1 ) reset $end
$var wire 1 ! in_ready $end
$var reg 17 @ data_out [16:0] $end
$var reg 1 A found $end
$var reg 6 B int_part [5:0] $end
$var reg 6 C msb_index [5:0] $end
$var reg 3 D next_state [2:0] $end
$var reg 1 9 out_valid $end
$var reg 48 E sample_reg [47:0] $end
$var reg 48 F shift_reg [47:0] $end
$var reg 3 G state [2:0] $end
$var reg 48 H zp_reg [47:0] $end
$var integer 32 I i [31:0] $end
$upscope $end
$scope module log_frac_calc_0 $end
$var wire 1 ' clk $end
$var wire 17 J data_in [16:0] $end
$var wire 1 5 in_valid $end
$var wire 1 6 out_ready $end
$var wire 1 ) reset $end
$var wire 1 < in_ready $end
$var reg 5 K cycle_count [4:0] $end
$var reg 5 L iter [4:0] $end
$var reg 17 M log_frac_out [16:0] $end
$var reg 2 N next_state [1:0] $end
$var reg 1 ; out_valid $end
$var reg 2 O state [1:0] $end
$var reg 17 P x [16:0] $end
$var reg 17 Q y [16:0] $end
$upscope $end
$upscope $end
$upscope $end
$enddefinitions $end
#0
$dumpvars
bx Q
bx P
bx O
b0 N
bx M
bx L
bx K
bx J
bx I
bx H
bx G
bx F
bx E
bx D
bx C
bx B
0A
bx @
bx ?
bx >
bx =
x<
x;
bx :
x9
x8
07
16
x5
bx 4
b0 3
b0 2
11
b0 0
b0 /
b0 .
1-
0,
bx +
b0 *
1)
b0 (
0'
bx &
bx %
bx $
b0 #
0"
x!
$end
#5
b0 D
1!
b0 G
05
09
b0 E
b0 &
b0 >
b0 M
b0 Q
b0 P
b0 K
b0 L
0;
18
1<
b0 O
1'
#10
0'
#15
1'
#20
0'
b111010110111100110100010110001 (
b111010110111100110100010110001 *
0)
#25
b1 .
b1 D
17
1"
01
b1 #
b1 0
b1 3
b111010110111100110100010110001 $
b111010110111100110100010110001 +
b111010110111100110100010110001 4
b111010110111100110100010110001 ?
1'
#30
0'
#35
b1 /
b10 .
b10 D
b1 2
b1 #
b1 0
b10 3
0!
b1 G
b111010110111100110100010110001 E
1'
#40
0'
#45
b11 .
b11 D
b10 #
b10 0
b11 3
b10 G
b111010110111100110100010110001 H
1'
#50
0'
#55
b100 .
b100 D
b11 #
b11 0
b100 3
b11 G
1A
b11101 C
b110000 I
1'
#60
0'
#65
b101 .
b101 D
b100 #
b100 0
b101 3
b100 G
b11101011011110011 F
1'
#70
0'
#75
b110 .
b0 D
b1 N
b101 #
b101 0
b110 3
b101 G
15
19
b11101011011110011 :
b11101011011110011 @
b11101011011110011 J
b11101 %
b11101 =
b11101 B
1'
#80
0'
#85
b111 .
b10 N
b1 D
b110 #
b110 0
b111 3
1!
b0 G
05
09
0A
08
0<
b1 O
1'
#90
0'
#95
b10 /
b1000 .
b10 D
b10 2
b110 #
b110 0
b1000 3
b1 K
b1 L
b11101011011110011 P
b10 O
0!
b1 G
1'
#100
0'
#105
b1001 .
b11 D
b111 #
b111 0
b1001 3
b10 G
b10 L
b10 K
b10000000000000000 Q
b1110101101111010 P
1'
#110
0'
#115
b1010 .
b100 D
b1000 #
b1000 0
b1010 3
b11 L
b11 K
b1010110110010111 Q
b10010011001011000 P
b11 G
1A
b11101 C
b110000 I
1'
#120
0'
#125
b1011 .
b101 D
b1001 #
b1001 0
b1011 3
b100 G
b100 L
b100 K
b1101111011011011 Q
b10000000110001101 P
1'
#130
0'
#135
b1100 .
b1010 #
b1010 0
b1100 3
b101 K
b1111011000101010 Q
b1111000101110101 P
b101 G
15
19
1'
#140
0'
#145
b1101 .
b1011 #
b1011 0
b1101 3
05
09
0A
b101 L
b110 K
b1101111111000111 Q
b10000000010001100 P
1'
#150
0'
#155
b1110 .
b1100 #
b1100 0
b1110 3
b110 L
b111 K
b1110101101010000 Q
b1111100010001000 P
1'
#160
0'
#165
b1111 .
b1101 #
b1101 0
b1111 3
b111 L
b1000 K
b1110010110010111 Q
b1111110001101010 P
1'
#170
0'
#175
b10000 .
b1110 #
b1110 0
b10000 3
b1000 L
b1001 K
b1110001010110111 Q
b1111111001100010 P
1'
#180
0'
#185
b10001 .
b1111 #
b1111 0
b10001 3
b1001 L
b1010 K
b1110000101000110 Q
b1111111101100000 P
1'
#190
0'
#195
b10010 .
b10000 #
b10000 0
b10010 3
b1010 L
b1011 K
b1110000010001101 Q
b1111111111011111 P
1'
#200
0'
#205
b10011 .
b10001 #
b10001 0
b10011 3
b1011 L
b1100 K
b1110000000110001 Q
b10000000000011110 P
1'
#210
0'
#215
b10100 .
b10010 #
b10010 0
b10100 3
b1100 L
b1101 K
b1110000001011111 Q
b1111111111111110 P
1'
#220
0'
#225
b10101 .
b10011 #
b10011 0
b10101 3
b1101 L
b1110 K
b1110000001001000 Q
b10000000000001101 P
1'
#230
0'
#235
b10110 .
b10100 #
b10100 0
b10110 3
b1110 L
b1111 K
b1110000001010011 Q
b10000000000000101 P
1'
#240
0'
#245
b10111 .
b10101 #
b10101 0
b10111 3
b1111 L
b10000 K
b1110000001011001 Q
b10000000000000001 P
1'
#250
0'
#255
b11000 .
b11 N
b10110 #
b10110 0
b11000 3
b10000 L
b10001 K
b1110000001011100 Q
b1111111111111111 P
1'
#260
0'
#265
b11001 .
b0 N
b10111 #
b10111 0
b11001 3
b10001 L
b10010 K
b1110000001011011 Q
b11 O
1'
#270
0'
#275
b11010 .
b0 D
b11000 #
b11000 0
b11010 3
1;
b1110000001011011 &
b1110000001011011 >
b1110000001011011 M
18
1<
b0 O
1'
#280
0'
#285
b11011 .
b1 D
b11001 #
b11001 0
b11011 3
1!
b0 G
0;
1'
#290
0'
#295
b11 /
b11100 .
b10 D
b11 2
b11001 #
b11001 0
b11100 3
0!
b1 G
1'
#300
0'
#305
b11101 .
b11 D
b11010 #
b11010 0
b11101 3
b10 G
1'
#310
0'
#315
b11110 .
b100 D
b11011 #
b11011 0
b11110 3
b11 G
1A
b11101 C
b110000 I
1'
#320
0'
#325
b11111 .
b101 D
b11100 #
b11100 0
b11111 3
b100 G
1'
#330
0'
#335
b0 .
b0 D
b1 N
b11101 #
b11101 0
b100000 3
b101 G
15
19
1'
#340
0'
#345
b1 .
b10 N
b1 D
b11110 #
b11110 0
b100001 3
1!
b0 G
05
09
0A
08
0<
b1 O
1'
#350
0'
#355
b100 /
b10 .
b10 D
b100 2
b11110 #
b11110 0
b100010 3
b1 K
b1 L
b0 Q
b11101011011110011 P
b10 O
0!
b1 G
1'
#360
0'
#365
b11 .
b11 D
b11111 #
b11111 0
b100011 3
b10 G
b10 L
b10 K
b10000000000000000 Q
b1110101101111010 P
1'
#370
0'
#375
1,
b100 .
b100 D
b100000 #
b100000 0
b100100 3
b11 L
b11 K
b1010110110010111 Q
b10010011001011000 P
b11 G
1A
b11101 C
b110000 I
1'
#380
0'
#385
b101 D
b100 G
b100 L
b100 K
b1101111011011011 Q
b10000000110001101 P
1'
#390
0'
#395
b101 K
b1111011000101010 Q
b1111000101110101 P
b101 G
15
19
1'
#400
0'
#405
05
09
0A
b101 L
b110 K
b1101111111000111 Q
b10000000010001100 P
1'
#410
0'
#415
b110 L
b111 K
b1110101101010000 Q
b1111100010001000 P
1'
#420
0'
#425
b111 L
b1000 K
b1110010110010111 Q
b1111110001101010 P
1'
#430
0'
#435
b1000 L
b1001 K
b1110001010110111 Q
b1111111001100010 P
1'
#440
0'
#445
b1001 L
b1010 K
b1110000101000110 Q
b1111111101100000 P
1'
#450
0'
#455
b1010 L
b1011 K
b1110000010001101 Q
b1111111111011111 P
1'
#460
0'
#465
b1011 L
b1100 K
b1110000000110001 Q
b10000000000011110 P
1'
#470
0'
#475
b1100 L
b1101 K
b1110000001011111 Q
b1111111111111110 P
1'
#480
0'
#485
b1101 L
b1110 K
b1110000001001000 Q
b10000000000001101 P
1'
#490
0'
#495
b1110 L
b1111 K
b1110000001010011 Q
b10000000000000101 P
1'
#500
0'
#505
b1111 L
b10000 K
b1110000001011001 Q
b10000000000000001 P
1'
#510
0'
#515
b11 N
b10000 L
b10001 K
b1110000001011100 Q
b1111111111111111 P
1'
#520
0'
#525
b0 N
b10001 L
b10010 K
b1110000001011011 Q
b11 O
1'
#530
0'
#535
b0 D
1;
18
1<
b0 O
1'
#540
0'
#545
b1 D
1!
b0 G
0;
1'
#550
0'
#555
0,
b101 /
b10 D
b11111 #
b11111 0
b101 2
0!
b1 G
1'
#560
0'
#565
1,
b101 .
b11 D
b100000 #
b100000 0
b100101 3
b10 G
1'
#570
0'
#575
b100 D
b11 G
1A
b11101 C
b110000 I
1'
#580
0'
#585
b101 D
b100 G
1'
#590
0'
#595
b0 D
b1 N
b101 G
15
19
1'
#600
0'
#605
b10 N
b1 D
1!
b0 G
05
09
0A
08
0<
b1 O
1'
#610
0'
#615
0,
b110 /
b10 D
b11111 #
b11111 0
b110 2
b1 K
b1 L
b0 Q
b11101011011110011 P
b10 O
0!
b1 G
1'
#620
0'
#625
1,
b110 .
b11 D
b100000 #
b100000 0
b100110 3
b10 G
b10 L
b10 K
b10000000000000000 Q
b1110101101111010 P
1'
#630
0'
#635
b100 D
b11 L
b11 K
b1010110110010111 Q
b10010011001011000 P
b11 G
1A
b11101 C
b110000 I
1'
#640
0'
#645
b101 D
b100 G
b100 L
b100 K
b1101111011011011 Q
b10000000110001101 P
1'
#650
0'
#655
b101 K
b1111011000101010 Q
b1111000101110101 P
b101 G
15
19
1'
#660
0'
#665
05
09
0A
b101 L
b110 K
b1101111111000111 Q
b10000000010001100 P
1'
#670
0'
#675
b110 L
b111 K
b1110101101010000 Q
b1111100010001000 P
1'
#680
0'
#685
b111 L
b1000 K
b1110010110010111 Q
b1111110001101010 P
1'
#690
0'
#695
b1000 L
b1001 K
b1110001010110111 Q
b1111111001100010 P
1'
#700
0'
#705
b1001 L
b1010 K
b1110000101000110 Q
b1111111101100000 P
1'
#710
0'
#715
b1010 L
b1011 K
b1110000010001101 Q
b1111111111011111 P
1'
#720
0'
#725
b1011 L
b1100 K
b1110000000110001 Q
b10000000000011110 P
1'
#730
0'
#735
b1100 L
b1101 K
b1110000001011111 Q
b1111111111111110 P
1'
#740
0'
#745
b1101 L
b1110 K
b1110000001001000 Q
b10000000000001101 P
1'
#750
0'
#755
b1110 L
b1111 K
b1110000001010011 Q
b10000000000000101 P
1'
#760
0'
#765
b1111 L
b10000 K
b1110000001011001 Q
b10000000000000001 P
1'
#770
0'
#775
b11 N
b10000 L
b10001 K
b1110000001011100 Q
b1111111111111111 P
1'
#780
0'
#785
b0 N
b10001 L
b10010 K
b1110000001011011 Q
b11 O
1'
#790
0'
#795
b0 D
1;
18
1<
b0 O
1'
#800
0'
#805
b1 D
1!
b0 G
0;
1'
#810
0'
#815
0,
b111 /
b10 D
b11111 #
b11111 0
b111 2
0!
b1 G
1'
#820
0'
#825
1,
b111 .
b11 D
b100000 #
b100000 0
b100111 3
b10 G
1'
#830
0'
#835
b100 D
b11 G
1A
b11101 C
b110000 I
1'
#840
0'
#845
b101 D
b100 G
1'
#850
0'
#855
b0 D
b1 N
b101 G
15
19
1'
#860
0'
#865
b10 N
b1 D
1!
b0 G
05
09
0A
08
0<
b1 O
1'
#870
0'
#875
0,
b1000 /
b10 D
b11111 #
b11111 0
b1000 2
b1 K
b1 L
b0 Q
b11101011011110011 P
b10 O
0!
b1 G
1'
#880
0'
#885
1,
b1000 .
b11 D
b100000 #
b100000 0
b101000 3
b10 G
b10 L
b10 K
b10000000000000000 Q
b1110101101111010 P
1'
#890
0'
#895
b100 D
b11 L
b11 K
b1010110110010111 Q
b10010011001011000 P
b11 G
1A
b11101 C
b110000 I
1'
#900
0'
#905
b101 D
b100 G
b100 L
b100 K
b1101111011011011 Q
b10000000110001101 P
1'
#910
0'
#915
b101 K
b1111011000101010 Q
b1111000101110101 P
b101 G
15
19
1'
#920
0'
#925
05
09
0A
b101 L
b110 K
b1101111111000111 Q
b10000000010001100 P
1'
#930
0'
#935
b110 L
b111 K
b1110101101010000 Q
b1111100010001000 P
1'
#940
0'
#945
b111 L
b1000 K
b1110010110010111 Q
b1111110001101010 P
1'
#950
0'
#955
b1000 L
b1001 K
b1110001010110111 Q
b1111111001100010 P
1'
#960
0'
#965
b1001 L
b1010 K
b1110000101000110 Q
b1111111101100000 P
1'
#970
0'
#975
b1010 L
b1011 K
b1110000010001101 Q
b1111111111011111 P
1'
#980
0'
#985
b1011 L
b1100 K
b1110000000110001 Q
b10000000000011110 P
1'
#990
0'
#995
b1100 L
b1101 K
b1110000001011111 Q
b1111111111111110 P
1'
#1000
0'
#1005
b1101 L
b1110 K
b1110000001001000 Q
b10000000000001101 P
1'
#1010
0'
#1015
b1110 L
b1111 K
b1110000001010011 Q
b10000000000000101 P
1'
